{
	"gdAcup":{
			"10001":{"id":10001,"deep":"0.1","dir":"浅刺，点刺出血","eff2":"清心利窍，泻热解表","ill":"热病，昏厥，头痛，目赤，耳聋，喉痹","jl":10,"nam":"关冲","team":"咽喉肿痛：少商，少泽；中暑：水沟，劳宫；热病无汗：风池，商阳","xw":"1"},
			"10002":{"id":10002,"deep":"0.5-1","dir":"直刺","ill":"头痛，目赤，耳鸣，耳聋，喉痹，热病，疟疾，手臂痛","jl":10,"nam":"液门","xw":"2"},
			"10003":{"id":10003,"deep":"0.3-0.5","dir":"直刺","eff2":"通络止痛，清头利窍，和解少阳","ill":"头痛，目赤，耳鸣，耳聋，喉痹，肩背肘臂疼痛麻木，手指不能屈伸，热病","jl":10,"nam":"中渚","team":"耳鸣，头痛：听宫，翳风；肩臂肘酸痛：肩髃，曲池，外关；肋间神经痛：外关，期门","xw":"3"},
			"10004":{"id":10004,"deep":"0.3-0.5","dir":"直刺","eff2":"通络止痛，清头利窍，养阴润燥","ill":"头痛，目赤肿痛，耳聋，喉痹，腕痛，消渴","jl":10,"nam":"阳池","team":"前臂疼痛：外关，曲池；咽喉疼痛：少商，廉泉；糖尿病：胃脘下俞，脾俞，太溪","xw":"6"},
			"10005":{"id":10005,"deep":"0.5-1","dir":"直刺","eff2":"清热利窍，通络止痛，清热解表，解表疏风，风寒暑湿等表症","ill":"头痛，颊痛，目赤肿痛，耳鸣，耳聋，热病，胁肋痛，上肢痹痛，瘰疬","jh":"阳维脉","jl":10,"nam":"外关","team":"偏头痛：太阳，率谷；落枕：后溪；手指疼痛，腕关节疼痛：阳池，中渚","warn":"手竖着扎","xw":"79"},
			"10006":{"id":10006,"deep":"0.5-1","dir":"直刺","eff2":"清热通便，清头利窍，通络利胁","ill":"便秘，胁肋痛，耳聋，耳鸣，暴瘖，瘰疬","jl":10,"nam":"支沟","team":"胸胁疼痛：阳陵泉，外关；便秘：足三里，天枢；手指震颤：阳池，八邪","xw":"4"},
			"10007":{"id":10007,"deep":"0.5-1","dir":"直刺","ill":"耳鸣，耳聋，上肢痹痛，癫痫","jl":10,"nam":"会宗","xw":"8"},
			"10008":{"id":10008,"deep":"0.8-1.2","dir":"直刺","ill":"上肢痹痛，耳聋，暴瘖，齿痛","jl":10,"nam":"三阳络"},
			"10009":{"id":10009,"deep":"0.5-1","dir":"直刺","ill":"手臂疼痛麻木，耳聋，暴瘖，齿痛，头痛","jl":10,"nam":"四渎"},
			"1001":{
					"id":1001,
					"danger":"4",
					"deep":"0.5-0.8",
					"dir":"向外斜刺，平刺",
					"eff2":"宣肺利气，通络止痛",
					"eff3":"2",
					"ill":"咳嗽，气喘，胸满痛，胸中烦满，肩背痛",
					"jh":"手太阴，足太阴",
					"jl":1,
					"m":"肺",
					"mix":"五壮",
					"nam":"中府",
					"team":"外感咳嗽，内伤咳嗽：肺俞；肺阴虚之干咳：复溜",
					"warn":"不可向内深刺，以免伤及肺脏，引起气胸"
				},
			"10010":{"id":10010,"deep":"0.5-1","dir":"直刺","ill":"手臂无力，上肢不遂，偏头痛，耳聋，胸胁痛，瘰疬","jl":10,"nam":"天井","xw":"5"},
			"10011":{"id":10011,"deep":"0.5-1","dir":"直刺","ill":"手臂臂痛，上肢不遂，头痛，目痛","jl":10,"nam":"清冷渊"},
			"10012":{"id":10012,"deep":"1-1.5","dir":"直刺","ill":"肩臂疼痛，麻木，头痛，齿痛，项强，癫痫","jl":10,"nam":"消泺"},
			"10013":{"id":10013,"deep":"1-1.5","dir":"直刺","ill":"上肢痹痛，瘰疬，瘿气","jl":10,"nam":"臑会"},
			"10014":{"id":10014,"deep":"1-1.5","dir":"向肩关节直刺","eff2":"疏经活络，祛风泄热","ill":"臂痛，肩重不能举，胁肋疼痛","jl":10,"nam":"肩髎","team":"肩臂痛：曲池，肩髃；肋间神经痛：外关，章门"},
			"10015":{"id":10015,"deep":"0.5-0.8","dir":"向肩关节直刺","ill":"肩臂痛，颈项强急","jl":10,"nam":"天髎"},
			"10016":{"id":10016,"deep":"0.5-1","dir":"直刺","ill":"头痛，项强，头晕，目痛，耳聋，瘰疬","jl":10,"nam":"天牖"},
			"10017":{"id":10017,"deep":"0.8-1.2","dir":"直刺","eff2":"聪耳利窍，祛风通络，化痰散结","ill":"口角歪斜，牙关紧闭，齿痛，颊肿，耳鸣，耳聋，瘰疬","jl":10,"nam":"翳风","team":"耳鸣，耳聋：听宫，听会；面瘫：地仓，颊车，阳白；颊痛：下关，颊车，合谷"},
			"10018":{"id":10018,"deep":"0.3-0.5","dir":"平刺，点刺出血","ill":"头痛，耳鸣，耳聋，小儿惊风","jl":10,"nam":"瘈脉"},
			"10019":{"id":10019,"deep":"0.3-0.5","dir":"平刺","ill":"头痛，耳鸣，耳聋，小儿惊风","jl":10,"nam":"颅息"},
			"1002":{"id":1002,"deep":"0.5-0.8","dir":"向外斜刺，平刺","ill":"咳嗽，气喘，胸痛，肩背痛，胸中烦痛","jl":1,"mix":"五壮","nam":"云门","team":" 主胸中痛：云门，中府，隐白，期门，肺俞，魂门，大陵"},
			"10020":{"id":10020,"deep":"0.3-0.5","dir":"平刺","ill":"颊肿，目翳，齿痛，项强","jl":10,"nam":"角孙"},
			"10021":{"id":10021,"deep":"0.5-1","dir":"张口直刺","eff2":"通窍聪耳，活络止痛，祛风解痉","ill":"耳鸣，耳聋，聤耳，齿痛","jl":10,"nam":"耳门","team":"耳鸣，耳聋，聤耳：听宫，听会，翳风；牙痛：下关，合谷，颊车；下颌关节炎：颧髎，颊车，翳风"},
			"10022":{"id":10022,"deep":"0.3-0.5","dir":"斜刺，平刺","ill":"头痛，耳鸣，牙关紧闭，口?","jl":10,"nam":"耳和髎","warn":"避开动脉"},
			"10023":{"id":10023,"deep":"0.5-1","dir":"平刺","eff2":"清热疏风，平肝熄风","ill":"目赤肿痛，眼睑瞤动，偏头痛，癫狂痫","jl":10,"nam":"丝竹空","team":"目赤肿痛：瞳子髎，睛明，攒竹；偏头痛：太阳，外关"},
			"1003":{"id":1003,"deep":"0.5-1","dir":"直刺","ill":"咳嗽，气喘，鼻衄，瘿气，上臂痛","jl":1,"mix":"禁灸","nam":"天府","team":"臂痛：曲池"},
			"1004":{"id":1004,"deep":"0.5-1","dir":"直刺","eff1":"赤白汗斑","ill":"咳嗽，气喘；干呕；上臂痛","jl":1,"mix":"五壮","nam":"侠白","team":"肩臂痛：曲池+肩髎"},
			"1005":{"id":1005,"deep":"0.5-0.8","dir":"直刺，点刺出血","eff2":"滋阴润肺，宽胸理气，通络止痛","ill":"咳嗽，气喘，咳血，咽喉肿痛，肘臂挛痛，急性吐泻，中暑，小儿惊风，夹脊旅痛（肺部肌肉）","jl":1,"mix":"五壮","nam":"尺泽","team":"咳嗽，气喘：列缺，肺俞；急性吐泻，中暑：委中","xw":"5"},
			"1006":{"id":1006,"deep":"0.5-0.8","dir":"直刺","eff2":"清热利肺，凉血止血，通络止痛","eff3":"5","ill":"痔疮出血，咯血，气喘，咽喉肿痛，肘臂挛痛，热病无汗，头痛，痔疮","jl":1,"mix":"五壮","nam":"孔最","team":"咳嗽，气喘：肺俞，风门；咽喉肿痛：少商","xw":"8"},
			"1007":{
					"id":1007,
					"deep":"0.2-0.3",
					"dir":"向患处方向斜刺",
					"eff1":"过敏（呼吸系统）",
					"eff2":"宣肺利气，祛风散邪",
					"ill":"手腕无力，小便热痛，咳嗽，气喘，咽喉肿痛，头痛，齿痛，项强，口眼?斜",
					"jh":"任脉",
					"jl":1,
					"mix":"七壮",
					"nam":"列缺",
					"team":"感冒，咳嗽，头痛：风池，风门；项强：合谷，外关；咽喉疼痛：照海",
					"xw":"79"
				},
			"1008":{"id":1008,"deep":"0.3～0.5","dir":"直刺","ill":"咳嗽，气喘，胸痛，咽喉肿痛，手腕痛","jl":1,"mix":"禁灸","nam":"经渠","team":"咳嗽：肺俞，尺泽","warn":"避开桡动脉"},
			"1009":{
					"id":1009,
					"bh":"脉会",
					"deep":"0.2-0.3",
					"dir":"直刺",
					"eff2":"宣肺利咽，益气复脉，通络止痛",
					"ill":"咳嗽，气喘，无脉症，腕臂痛",
					"jl":1,
					"mix":"三壮",
					"nam":"太渊",
					"team":"咳嗽，气喘，胸背痛：列缺，肺俞；无脉症：内关，三阴交",
					"warn":"避开桡动脉",
					"xw":"36"
				},
			"1010":{"id":1010,"deep":"0.5-0.8","dir":"直刺","eff2":"宣肺利咽，清热解表","ill":"咳嗽，咳血，咽干，咽喉肿痛，失音，小儿疳积","jl":1,"mix":"禁灸","nam":"鱼际","team":"肺热所致的咳嗽，咽喉肿痛，失音：合谷；哮喘发作：孔最，天突","xw":"2"},
			"1011":{"id":1011,"deep":"0.1","dir":"点刺出血，浅刺","eff2":"宣肺利咽，清热解暑，醒脑开窍，通络止痛","ill":"咽喉肿痛，鼻衄，高热，昏迷，癫狂","jl":1,"mix":"不宜","nam":"少商","team":"咽喉肿痛：合谷","xw":"1"},
			"11001":{"id":11001,"deep":"0.3-0.5","dir":"平刺，点刺出血","eff2":"清热明目，平肝熄风","ill":"目赤，目痛，目翳，头痛，口眼?斜","jl":11,"nam":"瞳子髎","team":"目痛，目赤，目翳：睛明，丝竹空，攒竹；头痛：头维，印堂，太冲"},
			"11002":{"id":11002,"deep":"0.5-1","dir":"直刺","eff2":"开窍聪耳，通络止痛","ill":"耳鸣，耳聋，聤耳，齿痛，口眼?斜，面痛","jl":11,"nam":"听会","team":"耳聋，耳鸣：听宫，翳风"},
			"11003":{"id":11003,"deep":"0.5-0.8","dir":"平刺","ill":"耳鸣，耳聋，聤耳，齿痛，面痛，偏头痛，口眼?斜，口噤，惊痫","jl":11,"nam":"上关（客主人）"},
			"11004":{"id":11004,"deep":"0.5-0.8","dir":"向后平刺","ill":"偏头痛，耳鸣，齿痛，眩晕，癫痫","jl":11,"nam":"颔厌"},
			"11005":{"id":11005,"deep":"0.5-0.8","dir":"向后平刺","ill":"偏头痛，齿痛，面肿，鼽衄","jl":11,"nam":"悬颅"},
			"11006":{"id":11006,"deep":"0.5-0.8","dir":"向后平刺","ill":"偏头痛，齿痛，面肿，耳鸣","jl":11,"nam":"悬厘"},
			"11007":{"id":11007,"deep":"0.5-0.8","dir":"向后平刺","ill":"偏头痛，齿痛，颌颊肿，目赤肿痛，眩晕","jl":11,"nam":"曲鬓"},
			"11008":{"id":11008,"deep":"0.5-1","dir":"平刺","ill":"偏头痛，眩晕，耳鸣，耳聋，小儿惊风","jl":11,"nam":"率谷"},
			"11009":{"id":11009,"deep":"0.5-1","dir":"平刺","ill":"头痛，耳鸣，耳聋，瘿气，惊恐，癫痫","jl":11,"nam":"天冲"},
			"11010":{"id":11010,"deep":"0.5-0.8","dir":"平刺","ill":"头痛，耳鸣，耳聋，瘿气，瘰疬","jl":11,"nam":"浮白"},
			"11011":{"id":11011,"deep":"0.5-0.8","dir":"平刺","ill":"欧通，眩晕，耳鸣，耳聋，瘿气","jl":11,"nam":"头窍阴"},
			"11012":{"id":11012,"deep":"0.5-0.8","dir":"斜刺","ill":"头痛，颊肿，口眼?斜，喉痹，齿痛，颈项强痛，癫痫，疟疾","jl":11,"nam":"完骨"},
			"11013":{"id":11013,"deep":"0.5-0.8","dir":"平刺","ill":"头痛，眩晕，癫痫，小儿惊风，中风，失眠","jl":11,"nam":"本神"},
			"11014":{"id":11014,"deep":"0.3-0.5","dir":"平刺","eff2":"疏风清热，通络明目","ill":"目赤肿痛，眼睑下垂，口眼?斜，头痛，抬头纹","jl":11,"nam":"阳白","team":"面瘫：颧髎，颊车，合谷；目赤肿痛：睛明，太阳"},
			"11015":{"id":11015,"deep":"0.3-0.5","dir":"平刺","eff2":"清热祛风，镇静宁神","ill":"头痛，目痛，目翳，鼻渊，小儿惊风，癫痫","jl":11,"nam":"头临泣","team":"头痛：百会，印堂，头维；目痛：阳白，太阳"},
			"11016":{"id":11016,"deep":"0.3-0.5","dir":"平刺","ill":"头痛，目赤肿痛，青芒，癫痫","jl":11,"nam":"目窗"},
			"11017":{"id":11017,"deep":"0.3-0.5","dir":"平刺","ill":"头痛，眩晕，齿痛","jl":11,"nam":"正营"},
			"11018":{"id":11018,"deep":"0.3-0.5","dir":"平刺","ill":"头痛，眩晕，鼻渊，鼻衅","jl":11,"nam":"承灵"},
			"11019":{"id":11019,"deep":"0.3-0.5","dir":"平刺","ill":"头痛，眩晕，颈项强痛，癫痫，惊悸","jl":11,"nam":"脑空"},
			"11020":{"id":11020,"deep":"0.8-1.2","dir":"针尖微下，向鼻尖方向斜刺，平刺透风府穴","eff2":"平肝熄风，清头利窍，祛风解表","ill":"头痛，眩晕，目赤肿痛，鼻渊，耳鸣，中风，失眠，癫痫，颈项强痛","jl":11,"nam":"风池","team":"颈项强痛：大椎，后溪；目赤肿痛：睛明，太阳，太冲"},
			"11021":{"id":11021,"deep":"0.3-0.5","dir":"直刺","eff2":"活络止痛，利风通乳","ill":"肩背臂痛，上肢不遂，颈项强痛，瘰疬，乳痈，乳汁不下，难产，胞衣不下","jl":11,"nam":"肩井","team":"肩背臂痛：肩髃，天宗；乳汁不足，乳痈：乳根，少泽","warn":"深部正当肺尖，慎不可深刺"},
			"11022":{"id":11022,"deep":"0.5-0.8","dir":"斜刺，平刺","ill":"胸满，胁痛，上肢痹痛","jl":11,"nam":"渊液"},
			"11023":{"id":11023,"deep":"0.5-0.8","dir":"斜刺，平刺","ill":"胸满，胁痛，气喘，呕吐，吞酸","jl":11,"nam":"辄筋"},
			"11024":{"id":11024,"deep":"0.5-0.8","dir":"斜刺","eff2":"疏肝利胆，通络止痛","ill":"黄疸，呕逆，呕吐，吞酸，胁肋疼痛，胃脘痛","jl":11,"m":"胆","nam":"日月","team":"黄疸：大椎，至阳，肝俞，阴陵泉；胁肋疼痛：丘墟，阳陵泉，支沟"},
			"11025":{"id":11025,"deep":"0.5-1","dir":"斜刺","ill":"小便不利，水肿，胁痛，腰痛，腹胀，腹泻，肠鸣，呕吐","jl":11,"m":"肾","nam":"京门"},
			"11026":{"id":11026,"deep":"0.8-1","dir":"斜刺","eff2":"调经止带，通络止痛","ill":"月经不调，带下，经闭，小腹痛，胁痛，腰痛","jl":11,"nam":"带脉","team":"带下病：白环俞，阴陵泉，三阴交"},
			"11027":{"id":11027,"deep":"1-1.5","dir":"直刺","ill":"带下，月经不调，阴挺，小腹痛","jl":11,"nam":"五枢"},
			"11028":{"id":11028,"deep":"1-1.5","dir":"直刺","ill":"带下，月经不调，阴挺，小腹痛，腹胯痛","jl":11,"nam":"维道"},
			"11029":{"id":11029,"deep":"1-1.5","dir":"直刺","ill":"腰胯疼痛，下肢痿痹，疝气","jl":11,"nam":"居髎"},
			"11030":{"id":11030,"deep":"2-3","dir":"直刺","eff2":"祛风通络","ill":"腰胯疼痛，下肢痿痹","jl":11,"nam":"环跳","team":"下肢痹痛：殷门，阳陵泉，委中，昆仑；风疹：风池，曲池"},
			"11031":{"id":11031,"deep":"1-1.5","dir":"直刺","eff2":"疏经活络，祛风止痒","ill":"下肢痿痹，遍身瘙痒，脚气","jl":11,"nam":"风市","team":"下肢痿痹：阳陵泉，悬钟；风疹：风池，曲池，血海"},
			"11032":{"id":11032,"deep":"1-1.5","dir":"直刺","ill":"下肢痿痹","jl":11,"nam":"中渎"},
			"11033":{"id":11033,"deep":"0.8-1","dir":"直刺","ill":"膝髌肿痛挛急，小腿麻木，脚气","jl":11,"nam":"膝阳关"},
			"11034":{"id":11034,"bh":"筋会","deep":"1-1.5","dir":"直刺","eff2":"疏肝利胆，通络止痛，息风止痉","ill":"黄疸，口苦，呕逆，呕吐，胁肋疼痛，下肢痿痹，膝髌肿痛，肩痛","jl":11,"nam":"阳陵泉","team":"胁肋痛：支沟；胆囊炎：日月；下肢痿痹：环跳，委中，悬钟","xh":"胆","xw":"5"},
			"11035":{"id":11035,"deep":"1-1.5","dir":"直刺","ill":"下肢痿痹，胸胁胀痛，癫狂","jl":11,"nam":"阳交","xw":"d"},
			"11036":{"id":11036,"deep":"1-1.5","dir":"直刺","ill":"下肢痿痹，胸胁胀痛，癫狂，颈项强痛","jl":11,"nam":"外丘","xw":"8"},
			"11037":{"id":11037,"deep":"1-1.5","dir":"直刺","eff2":"清肝明目，宽胸通乳","ill":"目痛，夜盲，目视不明，下肢痿痹，乳房胀痛，乳少","jl":11,"nam":"光明","team":"目痛：睛明，承泣，瞳子髎；青少年近视：太冲；可回乳：足临泣","xw":"7"},
			"11038":{"id":11038,"deep":"1-1.5","dir":"直刺","ill":"下肢痿痹，偏头痛，目外眦痛，腋下痛，胸胁痛，瘰疬，疟疾","jl":11,"nam":"阳辅","xw":"4"},
			"11039":{"id":11039,"bh":"髓会","deep":"1-1.5","dir":"直刺","eff1":"小腿酸痛，肌肉腓骨前缘，生髓：正对骨膜","eff2":"通络止痛，疏肝利胆，活血祛风","ill":"颈项强痛，胸胁胀痛，下肢痿痹，痴呆，中风","jl":11,"nam":"悬钟","team":"颈项强痛：天柱，后溪；眩晕，耳鸣：风池；高脂血症：丰隆"},
			"11040":{"id":11040,"deep":"0.5-0.8","dir":"直刺","eff2":"疏肝利胆，活血通络，清热截疟","ill":"胸胁胀痛，下肢痿痹，脚气，外踝肿痛，疟疾，疝气，中风偏瘫","jl":11,"nam":"丘墟","team":"外踝肿痛：昆仑，申脉；胸胁胀痛：阳陵泉，期门","xw":"6"},
			"11041":{"id":11041,"deep":"0.3-0.5","dir":"直刺","eff1":"肿瘤特效穴","eff2":"清利头目，调经通乳，疏肝利气，化痰散结，清热截疟","ill":"偏头痛，眩晕，目痛，外侧乳房胀痛，乳少，乳痈，胸胁胀痛，足跗肿痛，瘰疬，疟疾","jh":"带脉","jl":11,"nam":"足临泣","team":"偏头痛：外关，风池；乳房胀痛：光明；乳痈：乳根，肩井","xw":"39"},
			"11042":{"id":11042,"deep":"0.3-0.5","dir":"直刺","ill":"头痛，目赤肿痛，耳鸣，耳聋，胁痛，足跗肿痛，乳痈","jl":11,"nam":"地五会"},
			"11043":{"id":11043,"deep":"0.3-0.5","dir":"直刺","ill":"头痛，耳鸣，耳聋，目痛，眩晕，胸胁胀痛，足跗肿痛，热病","jl":11,"nam":"侠溪","xw":"2"},
			"11044":{"id":11044,"deep":"0.1-0.2","dir":"浅刺，点刺出血","eff2":"清利头目，宁心安神，清热解毒，疏肝消肿","ill":"头痛，目赤肿痛，耳鸣，耳聋，喉痹，失眠，多梦，胸胁胀痛，足跗肿痛","jl":11,"nam":"足窍阴","team":"耳鸣，耳聋：翳风，听会，外关；喉痹：少商，商阳","xw":"1"},
			"12001":{"id":12001,"deep":"0.1-0.2","dir":"浅刺，点刺出血","eff2":"疏肝理气，平肝熄风","ill":"疝气，经闭，崩漏，阴挺，遗尿，小便不利，癫痫","jl":12,"nam":"大敦","team":"疝气：太冲，气海，地机；崩漏：隐白；睾丸肿痛：太冲，曲泉","xw":"1"},
			"12002":{"id":12002,"deep":"0.5-0.8","dir":"直刺","eff2":"清肝明目，调经止崩，平肝熄风（偏肝阳上亢），疏肝利胆，泄肝火","ill":"中风，癫痫，头痛，目眩，目赤肿痛，青盲，口?，月经不调，痛经，崩漏，带下，遗尿，癃闭，疝气，胸胁胀痛","jl":12,"nam":"行间","team":"目赤肿痛：耳尖，太阳","xw":"2"},
			"12003":{"id":12003,"deep":"0.5-1","dir":"直刺","eff2":"清肝明目，调经止崩，平肝熄风，疏肝利胆，疏经活络","eff3":"泄肝火>行间","ill":"头痛，眩晕，目赤肿痛，青盲，口?，中风，癫痫，小儿惊风，黄疸，胁痛，口苦，腹胀，月经不调，痛经，经闭，带下，遗尿，癃闭，下肢痿痹，足跗肿痛","jl":12,"nam":"太冲","team":"头痛，眩晕，小儿惊风，口?：合谷（合谷+太冲=四关）","xw":"36"},
			"12004":{"id":12004,"deep":"0.5-0.8","dir":"直刺","ill":"疝气，腹痛，小便不利，遗精，下肢痿痹，足踝肿痛","jl":12,"nam":"中封","xw":"4"},
			"12005":{"id":12005,"deep":"0.5-0.8","dir":"平刺","ill":"月经不调，赤白带下，阴挺，睾丸肿痛，遗尿等妇科及前阴病症，勃起不软，疝气，小便不利，足胫疼痛","jl":12,"nam":"蠡沟","xw":"7"},
			"12006":{"id":12006,"deep":"0.5-0.8","dir":"平刺","ill":"疝气，小腹痛，崩漏，恶露不尽，胁痛，腹胀，下肢痿痹","jl":12,"nam":"中都","xw":"8"},
			"12007":{"id":12007,"deep":"0.8-1","dir":"直刺","ill":"西髌肿痛，下肢痿痹","jl":12,"nam":"膝关"},
			"12008":{"id":12008,"deep":"1-1.5","dir":"直刺","eff2":"利水通淋，通调冲任，通络止痛","ill":"小便不利，淋证，阳痿，遗精，月经不调，痛经，白带，阴挺，膝髌肿痛，下肢痿痹","jl":12,"nam":"曲泉","team":"小便不利：中极，阴陵泉；西髌肿痛：膝眼，梁丘，血海","xw":"5"},
			"12009":{"id":12009,"deep":"1-1.5","dir":"直刺","ill":"小便不利，遗尿，月经不调，腰痛，腰骶痛","jl":12,"nam":"阴包"},
			"12010":{"id":12010,"deep":"1-1.5","dir":"直刺","ill":"少腹胀痛，睾丸肿痛，小便不利，倦怠嗜卧","jl":12,"nam":"足五里"},
			"12011":{"id":12011,"deep":"1-1.5","dir":"直刺","ill":"月经不调，赤白带下，少腹疼痛，不孕（女性未生育，大腿打开，灸3次）","jl":12,"nam":"阴廉"},
			"12012":{"id":12012,"deep":"0.5-0.8","dir":"直刺","ill":"少腹痛，阴茎痛，阴挺，疝气","jl":12,"nam":"急脉","warn":"避开动脉"},
			"12013":{
					"id":12013,
					"bh":"脏会",
					"deep":"0.5-0.8，0.7-0.8",
					"dir":"斜刺，直刺",
					"eff2":"健脾消痞，疏肝利胆",
					"eff3":"（左侧>右侧，脾在左侧）",
					"ill":"胁痛，黄疸，腹胀，泄泻，呕吐，痞块",
					"jl":12,
					"m":"脾",
					"nam":"章门",
					"team":"腹胀：足三里，梁门；胸胁痛：内关，阳陵泉；肝脾肿大：肝俞，脾俞，期门，地机，太白，太冲",
					"warn":"缓慢进针，皮下脏腑"
				},
			"12014":{"id":12014,"deep":"0.5-0.8，0.7-0.8","dir":"斜刺，直刺","eff2":"疏肝利气，和胃降逆，解郁通乳","eff3":"（左侧<右侧，肝在左侧）","ill":"胸胁胀痛，腹胀，呕逆，呕吐，乳痈","jl":12,"m":"肝","nam":"期门","team":"胸胁胀痛：肝俞，膈俞；黄疸：阴陵泉，中封","warn":"缓慢进针，皮下脏腑"},
			"13001":{
					"id":13001,
					"deep":"0.5-1",
					"dir":"斜刺，针尖向上与骶骨平行刺入",
					"eff2":"止血固脱，通利腰脊，开窍宁神",
					"ill":"痔疾，脱肛，泄泻，便秘，肩背痛，癫狂痫，腰痛，尾骶骨痛，房劳，脑萎缩（帕金森）",
					"jh":"足少阴，足少阳",
					"jl":13,
					"mix":"五壮",
					"nam":"长强",
					"team":"便秘，痔疾：承山；脱肛：大肠俞，承山，百会；脑萎缩1，帕金森1：命门，大椎（针完灸长强，百会）；脑萎缩2，帕金森2：命门，大椎，脑户，百会（针完灸长强，百会）；脑萎缩3，帕金森3：命门，大椎，脑户，百会，太溪，悬钟（针完灸长强，百会）",
					"warn":"不得穿刺直肠，以防感染",
					"xw":"7"
				},
			"13002":{"id":13002,"jl":13,"mix":"七壮","nam":"腰俞"},
			"13003":{"id":13003,"deep":"0.5-1","dir":"直刺","eff2":"调血固精，壮腰健膝","ill":"腰骶疼痛，下肢痿痹，月经不调，带下，遗精，阳痿","jl":13,"mix":"三壮","nam":"腰阳关","team":"腰腿痛：肾俞，次髎，委中"},
			"13004":{"id":13004,"deep":"0.5-1，1.5","dir":"斜刺","eff2":"补肾培元，强壮腰脊","ill":"腰痛，下肢痿痹，遗精，阳痿，早泄，月经不调，赤白带下，遗尿，尿频，泄泻","jl":13,"mix":"三壮","nam":"命门","team":"肾虚尿多，腰酸背痛：肾俞；阳痿，早泄，滑精：肾俞，气海，然谷"},
			"13005":{"id":13005,"deep":"0.5-1","dir":"直刺","ill":"腹痛，泄泻，腰脊强痛","jl":13,"nam":"悬枢"},
			"13006":{"id":13006,"deep":"0.5-1","dir":"斜刺","ill":"泄泻，痔疾，腰脊强痛，癫痫","jl":13,"nam":"脊中"},
			"13007":{"id":13007,"deep":"0.5-1","dir":"斜刺","ill":"胃病，呕吐，腰背疼痛","jl":13,"nam":"中枢"},
			"13008":{"id":13008,"deep":"0.5-1","dir":"斜刺","ill":"脊强，癫痫，胃痛","jl":13,"nam":"筋缩"},
			"13009":{"id":13009,"deep":"0.5-1","dir":"斜刺","eff2":"疏肝利胆，止咳平喘，强壮腰脊","ill":"黄疸，胸胁胀痛，身热，咳嗽，气喘，胃痛，脊背强痛","jl":13,"nam":"至阳","team":"胸胁痛，黄疸，呕吐：阳陵泉，日月；心律不齐，胸闷，心俞，内关"},
			"13010":{"id":13010,"deep":"0.5-1","dir":"斜刺","ill":"疔疮，咳喘，胃痛","jl":13,"nam":"灵台"},
			"13011":{"id":13011,"deep":"0.5-1","dir":"斜刺","ill":"心悸，健忘，小儿惊痫","jl":13,"nam":"神道"},
			"13012":{"id":13012,"deep":"0.5-1","dir":"斜刺","ill":"咳喘，身热，癫痫","jl":13,"nam":"身柱"},
			"13013":{"id":13013,"deep":"0.5-1","dir":"斜刺","ill":"热病，疟疾，癫狂痫","jl":13,"nam":"陶道"},
			"13014":{"id":13014,"deep":"0.5-1","dir":"斜刺","eff2":"解表退热，止咳平喘，宁心安神，清热凉血，强壮腰脊","ill":"热病，疟疾，感冒，咳嗽，气喘，癫痫，小儿惊风，头项强痛，风疹，痤疮","jl":13,"nam":"大椎","team":"感冒：曲池，列缺，风门；疟疾：后溪，间使"},
			"13015":{"id":13015,"deep":"0.5-1","dir":"伏案正坐位，使头微前倾，项肌放松，向下颌方向缓慢刺入","eff2":"开音利喉，宁心安神，通络止痛","ill":"暴瘖，舌强不语（偏脑问题），癫狂痫，头痛，项强","jl":13,"nam":"哑门","team":"癫痫：水沟，腰奇；聋哑：廉泉，耳门，翳风，合谷"},
			"13016":{"id":13016,"danger":"5","deep":"0.5-1","dir":"伏案正坐位，使头微前倾，项肌放松，向下颌方向缓慢刺入","eff2":"醒神开窍，疏风清脑","ill":"头痛，眩晕，项强，中风不语，半身不遂，癫狂痫","jl":13,"nam":"风府","team":"头痛：百会，太阳，昆仑；小儿惊风：风池，水沟，太冲，合谷","warn":"针尖不可向上，以免刺入枕骨大孔，误伤延髓"},
			"13017":{"id":13017,"deep":"0.5-1","dir":"平刺","ill":"头痛，眩晕，癫痫","jl":13,"nam":"脑户"},
			"13018":{"id":13018,"deep":"0.5-0.8","dir":"平刺","ill":"头痛，目眩，癫狂，失眠","jl":13,"nam":"强间"},
			"13019":{"id":13019,"deep":"0.5-1","dir":"平刺","ill":"头痛，眩晕，癫狂痫","jl":13,"nam":"后顶"},
			"13020":{"id":13020,"deep":"0.5-1","dir":"平刺","eff2":"醒脑开窍，宁心安神，平肝潜阳","ill":"头痛，眩晕，中风失语，癫狂痫，失眠，健忘，脱肛，阴挺，久泻","jl":13,"nam":"百会","team":"头风，眼花：脑空，天柱；脱肛，痔疾：承山，长强；久泻下陷：脾俞"},
			"13021":{"id":13021,"deep":"0.3-0.5","dir":"平刺","ill":"头痛，眩晕，癫狂痫，中风偏瘫","jl":13,"nam":"前顶"},
			"13022":{"id":13022,"danger":"小儿5","deep":"0.3-0.5","dir":"平刺","ill":"头痛，眩晕，癫痫","jl":13,"nam":"囟会","warn":"小儿禁刺"},
			"13023":{"id":13023,"deep":"0.5-0.8","dir":"平刺","eff2":"清脑通窍，宁心安神，清热截疟","ill":"鼻渊，鼻衅，目痛，头痛，眩晕，癫狂，热病，疟疾","jl":13,"nam":"上星","team":"鼻塞不闻香臭，头痛：百会，囟会，承光；鼻渊，眩晕：合谷，足三里"},
			"13024":{"id":13024,"deep":"0.3-0.5","dir":"平刺","ill":"头痛，眩晕，失眠，鼻渊，流泪，目痛","jl":13,"nam":"神庭"},
			"13025":{"id":13025,"deep":"0.3-0.5","dir":"向上斜刺，点刺出血","eff2":"宣通鼻窍，苏觉救逆","ill":"鼻塞，鼻渊，鼻衅，酒糟鼻，惊厥，昏迷，窒息","jl":13,"nam":"素髎","team":"鼻衅：上星，迎香；休克：内关，足三里"},
			"13026":{"id":13026,"deep":"0.3-0.5","dir":"向上斜刺，掐","eff2":"苏觉开窍，息风止痉，通利腰脊，祛风通络","ill":"昏迷，晕厥，中风，癫狂痫，口?，牙关紧闭，闪挫腰痛，脊膂强痛，消渴，黄疸，遍身水肿","jl":13,"nam":"水沟","team":"鼻衅：上星，迎香；休克：内关，足三里"},
			"13027":{"id":13027,"deep":"0.2-0.3","dir":"斜刺","ill":"口?，齿龈肿痛，癫疾，昏厥，腰脊强痛","jl":13,"nam":"兑端"},
			"13028":{"id":13028,"deep":"0.2-0.3","dir":"向上斜刺","ill":"赤影中通，腰痛，痔疾","jl":13,"nam":"龈交"},
			"13029":{"id":13029,"deep":"0.3-0.5","dir":"提捏局部皮肤，向下平刺，点刺出血","eff2":"醒脑镇惊，活络通窍","ill":"头痛，眩晕，鼻渊，鼻衅，目赤肿痛，小儿惊风，失眠","jl":13,"nam":"印堂"},
			"14001":{"id":14001,"deep":"0.5-1","dir":"直刺","ill":"小便不利，遗尿，遗精，阳痿，月经不调，溺水，窒息，产后昏迷，癫狂","jl":14,"nam":"会阴"},
			"14002":{"id":14002,"deep":"0.5-1","dir":"直刺","ill":"月经不调，痛经，带下，小便不利，遗尿，遗精，阳痿","jl":14,"nam":"曲骨","warn":"排尿后针刺，孕妇禁针"},
			"14003":{"id":14003,"deep":"1-1.5","dir":"直刺","eff2":"通利小便，益肾调经","ill":"癃闭，遗尿，尿频，月经不调，带下，痛经，阴挺，遗精，阳痿","jl":14,"m":"膀胱","nam":"中极","team":"痛经：地极，次髎；遗精，阳痿，调节内分泌：关元，三阴交","warn":"孕妇禁针"},
			"14004":{"id":14004,"deep":"1","dir":"直刺","eff2":"积冷虚乏皆宜，诸虚百损，升阳举陷，益肾调经，通利小便，健脾止泻","ill":"阳痿，遗精，遗尿，癃闭，尿频，月经不调，痛经，闭经，崩漏，带下，不孕，腹痛，泄泻，痢疾，虚劳赢瘦，中风脱证","jl":14,"m":"小肠","nam":"关元","team":"遗尿：中极，百会，三阴交；肾虚尿频：肾俞，气海；久痢：肾俞，太溪","warn":"排尿后针刺，孕妇慎用"},
			"14005":{"id":14005,"deep":"1-2","dir":"直刺","ill":"小便不利，遗精，阳痿，产后恶露不尽，腹痛，腹胀，水肿","jl":14,"m":"三焦","nam":"石门","warn":"孕妇慎用"},
			"14006":{"id":14006,"deep":"1-2","dir":"直刺","eff2":"升阳补气，益肾调经，通调二便，脏器虚疲，真气不足","ill":"腹痛，泄泻，便秘，遗尿，遗精，阳痿，闭经，痛经，崩漏，带下，阴挺，虚劳赢瘦，中风脱证","jl":14,"nam":"气海","team":"中气下陷：关元，足三里；急性痢疾：天枢，上巨虚；气短：膻中，太渊"},
			"14007":{"id":14007,"deep":"1-2","dir":"直刺","ill":"腹痛，水肿，月经不调","jl":14,"nam":"阴交"},
			"14008":{"id":14008,"dir":"禁刺，宜灸","eff2":"回阳固脱，健脾利湿","ill":"腹痛，久泻，痢疾，脱肛，虚脱，水肿，小便不利","jl":14,"nam":"神阙","team":"中气下陷：关元，足三里；急性痢疾：天枢，上巨虚；气短：膻中，太渊"},
			"14009":{"id":14009,"deep":"1-2","dir":"直刺","ill":"腹痛，泄泻，翻胃，水肿，腹胀","jl":14,"nam":"水分"},
			"14010":{"id":14010,"deep":"1-2","dir":"直刺","eff2":"健脾和胃","ill":"腹痛，腹胀，食古不化，呕吐，谢谢，虚肿，消瘦","jl":14,"nam":"下脘","team":"腹坚硬胀痞块：中脘；痢疾：灸下脘，天枢，照海"},
			"14011":{"id":14011,"jl":14,"nam":"建里"},
			"14012":{"id":14012,"bh":"腑会","deep":"1-1.5","dir":"直刺","eff2":"健脾和胃，宁心安神，疏肝利胆","ill":"胃痛，呕吐，吞酸，腹胀，谢谢，黄疸","jl":14,"m":"胃","nam":"中脘","team":"霍乱吐泻：天枢，足三里，内庭；脘腹胀满：足三里"},
			"14013":{"id":14013,"deep":"1-1.5","dir":"直刺","ill":"胃痛，呕吐，吞酸，癫狂痫","jl":14,"nam":"上脘"},
			"14014":{"id":14014,"deep":"0.3-0.6","dir":"直刺","ill":"胃痛，呕吐，吞酸，胸痛","jl":14,"m":"心","nam":"巨阙"},
			"14015":{"id":14015,"deep":"0.3-0.6","dir":"直刺","ill":"胸闷，心痛，噎嗝，癫狂痫","jl":14,"nam":"鸠尾","xw":"7"},
			"14016":{"id":14016,"deep":"0.3-0.5","dir":"直刺","ill":"心痛，呕吐，小儿吐乳","jl":14,"nam":"中庭"},
			"14017":{"id":14017,"bh":"气会","deep":"0.3-0.5","dir":"直刺，平刺","eff2":"止咳平喘，宽胸通乳，和胃降逆","ill":"胸闷，气短，胸痛，心悸，咳嗽，气喘，乳汁少，乳痈，呕逆，呕吐","jl":14,"m":"心包","nam":"膻中","team":"哮喘：定喘，天突；心绞痛：心俞，内关；气虚：百会，气海"},
			"14018":{"id":14018,"deep":"0.3-0.5","dir":"直刺","ill":"胸痛，胸闷，咳喘","jl":14,"nam":"玉堂"},
			"14019":{"id":14019,"deep":"0.3-0.5","dir":"直刺","ill":"胸痛，胸闷，咳喘","jl":14,"nam":"紫宫"},
			"14020":{"id":14020,"deep":"0.3-0.5","dir":"直刺","ill":"胸痛，咳喘","jl":14,"nam":"华盖"},
			"14021":{"id":14021,"deep":"0.3-0.5","dir":"直刺","ill":"咳喘，胸痛，胃中积滞","jl":14,"nam":"璇玑"},
			"14022":{"id":14022,"deep":"0.2，0.5-1","dir":"直刺+下刺","eff2":"宣肺理气，开音利喉，行气散结","ill":"咽喉肿痛，暴瘖，瘿气，梅核气，噎嗝","jl":14,"nam":"天突","team":"哮喘：定喘，丰隆","warn":"先直刺0.2寸，当针尖超过胸骨柄内缘后，即向下沿胸骨柄后缘，气管前缘缓慢向下刺入0.5-1寸"},
			"14023":{"id":14023,"deep":"0.5-0.8","dir":"针尖向咽喉部刺入","eff2":"开音利喉","ill":"舌强不语（偏舌头问题），舌下肿痛，舌纵涎出，口舌生疮，暴瘖，吞咽困难，咽喉肿痛","jl":14,"nam":"廉泉","team":"舌下肿痛：中冲"},
			"14024":{"id":14024,"deep":"0.5-0.5","dir":"斜刺","eff2":"祛风泻火，宁心安神","ill":"口?，唇紧，齿龈肿痛，流涎，口舌成疮，面痛，消渴，癫痫","jl":14,"nam":"承浆","team":"口舌生疮，口臭，口干：劳宫"},
			"2001":{"id":2001,"deep":"0.1","dir":"点刺出血，浅刺","eff2":"清热利窍，舒筋活血","ill":"齿痛，咽喉肿痛，热病，昏迷","mix":"三壮","nam":"商阳","team":"热病，昏迷：少商，水沟；咽喉肿痛：少商，合谷","xw":"1"},
			"2002":{"id":2002,"deep":"0.2-0.3","dir":"直刺","ill":"鼻衄，齿痛，热病","mix":"三壮","nam":"二间","xw":"2"},
			"2003":{"id":2003,"deep":"0.3-0.5","dir":"直刺","eff2":"清热利窍，舒筋活络","ill":"齿痛，咽喉肿痛，腹胀，腹痛，肠鸣，泄泻","mix":"三壮","nam":"三间","team":"目急痛：前谷，睛明；痹咽如梗：阳溪；腹满，肠鸣，洞泄：天枢，足三里","xw":"3"},
			"2004":{"id":2004,"deep":"0.5-1","dir":"直刺","eff2":"镇痛利窍，清热解表，调经利产，舒筋活络","ill":"寒热痹痛；痛无定处；癌症疼痛，头痛，目赤肿痛，鼻衄，齿痛，口眼?斜，耳聋，发热恶寒外感病症，热病无汗或多汗，经闭，滞产","mix":"三壮","nam":"合谷","team":"头痛：太阳；目赤肿痛：太冲；鼻疾：迎香；咽喉肿痛：少商；经闭，滞产：三阴交；口眼涡斜：地仓，颊车；","warn":"孕妇禁针","xw":"6"},
			"2005":{"id":2005,"deep":"0.5-0.8","dir":"直刺","eff2":"清热利窍，舒筋活络","ill":"腱鞘炎，肌腱炎，鼠标手，手腕痛，头痛，目赤肿痛，耳聋，齿痛，咽喉肿痛","mix":"三壮","nam":"阳溪","team":"头痛：合谷；腕关节炎：阳池，阳谷","xw":"4"},
			"2006":{"id":2006,"deep":"0.5-0.8","dir":"直刺，斜刺","eff2":"清热利窍，利水消肿，舒筋活络","ill":"耳鸣，鼻衄，喉痛，手臂酸痛，腹部胀痛，水肿","mix":"三壮","nam":"偏历","team":"咽喉痛：太渊；手臂疼痛：曲池","xw":"7"},
			"2007":{"id":2007,"deep":"0.5-1","dir":"直刺","ill":"明目聪耳，腹部胀满，腹部水肿，肠鸣腹痛，疔疮，头痛，面肿，咽喉肿痛，肩背酸痛","mix":"三壮","nam":"温溜"},
			"2008":{"id":2008,"deep":"0.5-1","dir":"直刺","ill":"肘臂痛，头痛，眩晕，目痛，腹胀，腹痛","mix":"三壮","nam":"下廉"},
			"2009":{"id":2009,"deep":"0.5-1","dir":"直刺","ill":"肩臂酸痛，半身不遂，手臂麻木，头痛，肠鸣腹痛","mix":"五壮","nam":"上廉"},
			"2010":{"id":2010,"deep":"1-1.5","dir":"直刺","eff2":"舒筋活络，理气通腑，清热止痛","ill":"手臂无力，上肢不遂，腹痛，腹泻，齿痛，颊肿","mix":"三壮","nam":"手三里","team":"上肢不遂：曲池；腹痛，腹胀，腹泻：足三里；咽喉肿痛：中渚，足三里"},
			"2011":{"id":2011,"deep":"0.8-1.2","dir":"直刺","eff2":"清热利窍，舒筋活络，祛风凉血，理气通腑，活血调经","ill":"清热，淋巴瘤，瘰疬（淋巴结核），皮肤干燥，手臂臂痛，上肢不遂，热病，高血压，癫狂，腹痛吐泻，咽喉肿痛，齿痛，目赤痛，瘾诊，湿疹","mix":"三壮*，七壮*","nam":"曲池","team":"瘾诊：血海，足三里；上肢不遂：足三里；高血压：太冲，高血压","xw":"5"},
			"2012":{"id":2012,"deep":"0.5-1","dir":"直刺","ill":"肘臂部痪痛，麻木，挛急","mix":"三壮","nam":"肘髎"},
			"2013":{"id":2013,"deep":"0.5-1","dir":"直刺","ill":"肘臂挛痛，瘰疬","mix":"十壮","nam":"手五里","warn":"避开动脉，《素问》大禁针"},
			"2014":{"id":2014,"deep":"0.8-1.5","dir":"直刺，向上斜刺","eff2":"通络止痛，消瘰结散，清热明目","ill":"肩臂疼痛，上肢不遂，颈项拘挛，瘰疬，目疾","mix":"七壮","nam":"臂臑","team":"目疾：光明；颈瘰疬：曲池，手三里"},
			"2015":{"id":2015,"deep":"0.8-1.5","dir":"直刺，向上斜刺","eff2":"通络止痛，消瘰结散，活血祛风","ill":"肩臂挛痛，上肢不遂，瘾诊","jh":"手阳明","mix":"七壮","nam":"肩髃","team":"肩臂疼痛：肩髎，臂臑；偏瘫：曲池，阳陵泉，绝谷；风热瘾诊：曲池"},
			"2016":{"id":2016,"deep":"0.5-1","dir":"直刺，微斜向外下方","ill":"肩臂挛痛，上肢不遂，瘰疬，瘿气","jh":"手阳明，阳跷脉","mix":"七壮","nam":"巨骨"},
			"2017":{"id":2017,"deep":"0.5-0.8","dir":"直刺","ill":"暴瘖气梗，咽喉肿痛，瘰疬，瘿气","mix":"三壮","nam":"天鼎"},
			"2018":{"id":2018,"deep":"0.5-0.8","dir":"直刺","eff2":"清热利咽，理气结散，止咳平喘","ill":"咽喉肿痛，暴?，瘰疬，瘿气，咳嗽，气喘","mix":"三壮","nam":"扶突","team":"瘿气：合谷；咽喉肿痛：大椎，曲池，合谷；喘息，喉中痰鸣","warn":"避开桡动脉，不可深刺，不使用电针，以免引起迷走神经中枢反应"},
			"2019":{"id":2019,"mix":"禁灸","nam":"口禾髎"},
			"2020":{"id":2020,"deep":"0.3-0.5","dir":"向内上方斜刺，平刺","eff2":"通利鼻窍，散风通络，杀虫止痛","ill":"鼻塞，鼽衄，口?，面痒，胆道蛔虫病","jh":"手阳明，足阳明","mix":"禁灸","nam":"迎香","team":"急性鼻炎，慢性鼻炎：印堂，合谷；面痒肿：合谷；面神经麻痹：四白，地仓，颊车"},
			"3001":{"id":3001,"danger":"4","deep":"0.5-0.7","dir":"直刺","eff2":"清热明目，疏风止痉","ill":"（下）眼睑瞤动，迎风流泪，目赤肿痛，夜盲，口眼?斜，面肌痉挛","jl":3,"nam":"承泣","team":"目赤肿痛：太阳；口眼?斜：阴白，合谷，颊车，地仓","warn":"患者闭眼，医者押拇指向上轻推眼球固定，刺手持针紧靠眶缘缓慢直刺，不宜提插，以防刺破血管引起血肿。出针时按压针孔片刻，以防出血"},
			"3002":{"id":3002,"deep":"0.3-0.5","dir":"直刺，微向上斜刺","eff2":"清热明目，疏风止痉，通络止痛","ill":"目赤痛痒，目翳，眼睑瞤动，口眼?斜，面肌痉挛，头痛，眩晕，下眼袋下垂","jl":3,"nam":"四白","team":"口眼?斜：阴白，地仓，颊车，合谷；眼睑瞤动：攒竹","warn":"不可深刺，不可过度提插捻转"},
			"3003":{"id":3003,"deep":"0.3-0.5","dir":"斜刺，平刺","ill":"口眼?斜，眼睑瞤动，鼻衄，齿痛，唇颊肿","jl":3,"nam":"巨髎"},
			"3004":{"id":3004,"deep":"0.5-0.8","dir":"斜刺，平刺，可向迎香，颊车方向透刺","eff2":"疏风止痉，通络止痛","ill":"口?，流涎，眼睑瞤动，口腔溃疡","jl":3,"nam":"地仓","team":"口?，流涎：颊车，四白"},
			"3005":{"id":3005,"deep":"0.3-0.5","dir":"斜刺，平刺","ill":"口?，口噤，颊肿，齿痛","jl":3,"nam":"大迎","warn":"避开动脉"},
			"3006":{"id":3006,"deep":"0.3-0.5或0.5-1","dir":"直刺，平刺","eff2":"祛风止痉，通络止痛","ill":"口?，齿痛，颊肿，口噤不语，下齿下颌病","jl":3,"nam":"颊车","team":"口眼?斜：地仓；胃火牙疼：合谷，内庭；肾虚牙疼：太溪","warn":"可向地仓方向透刺"},
			"3007":{"id":3007,"deep":"0.5-1","dir":"直刺","eff2":"祛风止痛，聪耳通络","ill":"耳聋，耳鸣，聤耳（中耳炎），齿痛，口噤，口眼?斜，上齿上颌病","jl":3,"nam":"下关","team":"耳疾：翳风，耳门；面瘫：颊车，大迎；牙关紧闭：合谷，外关，翳风"},
			"3008":{"id":3008,"deep":"0.5-1","dir":"平刺","eff2":"通络止痛，疏风明目","ill":"头痛，目眩，目痛，流泪","jl":3,"nam":"头维","team":"头痛：合谷；目眩：太冲"},
			"3009":{"id":3009,"deep":"0.3-0.8","dir":"直刺","ill":"瘿气，瘰疬，咽喉肿痛，高血压，气喘","jl":3,"nam":"人迎","warn":"避开颈动脉"},
			"3010":{"id":3010,"deep":"0.3-0.8","dir":"直刺","ill":"咽喉肿痛，咳嗽，气喘","jl":3,"nam":"水突"},
			"3011":{"id":3011,"deep":"0.3-0.5","dir":"直刺","ill":"咽喉肿痛，瘿瘤，瘰疬，气喘，呃逆，颈项强痛","jl":3,"nam":"气舍"},
			"3012":{"id":3012,"deep":"0.3-0.5","dir":"直刺，斜刺","ill":"咳嗽，气喘，咽喉肿痛，缺盆中痛，瘰疬","jl":3,"nam":"缺盆"},
			"3013":{"id":3013,"deep":"0.5-0.8","dir":"直刺，斜刺","ill":"咳嗽，气喘，呃逆，胸肋支满，胸痛","jl":3,"nam":"气户"},
			"3014":{"id":3014,"deep":"0.5-0.8","dir":"直刺，斜刺","ill":"咳嗽，气喘，咳唾脓血，胸肋胀痛","jl":3,"nam":"库房"},
			"3015":{"id":3015,"deep":"0.5-0.8","dir":"直刺，斜刺","ill":"咳嗽，气喘，咳唾脓血，胸肋胀痛，乳痈","jl":3,"nam":"屋翳"},
			"3016":{"id":3016,"deep":"0.5-0.8","dir":"直刺，斜刺","ill":"咳嗽，气喘，胸肋胀痛，乳痈","jl":3,"nam":"膺窗"},
			"3017":{"id":3017,"dir":"只做定位标志","ill":"只做定位标志","jl":3,"nam":"乳中"},
			"3018":{"id":3018,"deep":"0.5-0.8","dir":"直刺，斜刺","ill":"乳痈，乳汁少，咳嗽，气喘，呃逆，胸痛","jl":3,"nam":"乳根"},
			"3019":{"id":3019,"deep":"0.5-0.8","dir":"直刺，斜刺","ill":"呕吐，胃病，食欲不振，腹胀","jl":3,"nam":"不容"},
			"3020":{"id":3020,"deep":"0.8-1","dir":"直刺，斜刺","ill":"胃痛，吐血，食欲不振，腹胀","jl":3,"nam":"承满"},
			"3021":{"id":3021,"deep":"0.8-1.2","dir":"直刺","eff2":"消积和胃","ill":"胃痛，呕吐，食欲不振，食多不消化","jl":3,"nam":"梁门","team":"胃痛：梁丘，中脘，足三里；反酸，呕吐：梁门，日月","warn":"不宜大幅度提插"},
			"3022":{"id":3022,"deep":"0.8-1.2","dir":"直刺","ill":"腹胀，腹痛，肠鸣泄泻，水肿","jl":3,"nam":"关门"},
			"3023":{"id":3023,"deep":"0.8-1.2","dir":"直刺","ill":"胃病，心烦，癫狂","jl":3,"nam":"太乙"},
			"3024":{"id":3024,"deep":"0.8-1.2","dir":"直刺","ill":"胃病，呕吐，癫狂","jl":3,"nam":"滑肉门"},
			"3025":{"id":3025,"deep":"1-1.5","dir":"直刺","eff2":"通腑理肠，调经止痛","ill":"腹胀肠鸣，绕脐痛，便秘，泄泻，痢疾，月经不调，痛经","jl":3,"m":"大肠","nam":"天枢","team":"腹胀肠鸣：足三里；绕脐痛：气海；便秘，泄泻：上巨虚，下巨虚；痛经：中极，三阴交，太冲；瘦腰：大横，带脉，水道"},
			"3026":{"id":3026,"deep":"1-1.5","dir":"直刺","ill":"腹痛，疝气，痛经","jl":3,"nam":"外陵"},
			"3027":{"id":3027,"deep":"1-1.5","dir":"直刺","ill":"小腹胀满，小便不利，疝气，遗精，早泄","jl":3,"nam":"大巨"},
			"3028":{"id":3028,"deep":"1-1.5","dir":"直刺","ill":"小腹胀满，水肿，小便不利，疝气，痛经，不孕","jl":3,"nam":"水道"},
			"3029":{"id":3029,"deep":"1-1.5","dir":"直刺","eff2":"理气止痛，调经止带，益气升提","ill":"腹痛，疝气，月经不调，白带，阴挺，中气下垂","jl":3,"nam":"归来","team":"疝气：大敦，太冲；月经不调：三阴交，中极；子宫下垂：百会，气海，三阴交"},
			"3030":{"id":3030,"deep":"0.5-1","dir":"直刺","ill":"肠鸣腹痛，疝气，月经不调，不孕，阳痿，阴肿","jl":3,"nam":"气冲"},
			"3031":{"id":3031,"deep":"1-2","dir":"直刺","ill":"腰痛膝冷，下肢痿痹，腹痛","jl":3,"nam":"髀关"},
			"3032":{"id":3032,"deep":"1-2","dir":"直刺","eff2":"舒筋通络，壮腰健膝","ill":"腰痛西冷，下肢麻痹，疝气，脚气（脚酸软无力，非香港脚）","jl":3,"nam":"伏兔","team":"下肢痿痹：髀关，阳陵泉；腿膝疼痛：环跳，犊鼻"},
			"3033":{"id":3033,"deep":"1-1.5","dir":"直刺","ill":"腿膝痿痹，屈伸不利，疝气，腹胀腹痛","jl":3,"nam":"阴市"},
			"3034":{"id":3034,"deep":"1-1.2","dir":"直刺","eff2":"和胃止痛，舒筋活络，宽胸通乳，乳腺增生（中线部分，中后期，前期胆经开始）","ill":"急性胃痛，膝肿痛，下肢不遂，乳痈","jl":3,"nam":"梁丘","team":"胃痛：足三里，中脘；急性腹泻：艾灸此穴；膝关节不得屈伸：膝阳关，阳陵泉","xw":"8"},
			"3035":{"id":3035,"deep":"0.5-1","dir":"向后内斜刺","ill":"膝痛，下肢麻痹，屈伸不利，脚气（脚酸软无力，非香港脚）","jl":3,"nam":"犊鼻"},
			"3036":{"id":3036,"deep":"1-2","dir":"直刺","eff2":"健脾和胃，舒筋活络，祛痰镇静，消痈止痛，强壮保健","ill":"胃痛，呕吐，噎嗝，腹胀，泄泻，痢疾，便秘，乳痈，肠痈，下肢痹痛，水肿，癫狂，脚气，虚劳赢瘦","jl":3,"nam":"足三里","team":"胃痛：中脘，梁丘：呕吐：内关；腹胀：气海；乳痛：膻中，乳根；下肢痹痛：阳陵泉，悬钟","xh":"胃","xw":"5"},
			"3037":{"id":3037,"deep":"1-2","dir":"直刺","eff2":"通腑理肠，舒筋活络","ill":"肠鸣，腹痛，泄泻，便秘，肠痈，下肢痿痹，脚气","jl":3,"nam":"上巨虚","team":"便秘，泄泻：足三里，气海；肠痈：天枢，阑尾穴，足三里","xh":"大肠"},
			"3038":{"id":3038,"deep":"1-1.5","dir":"直刺","ill":"下肢痿痹，转筋，肩臂痛，脘腹疼痛","jl":3,"nam":"条口"},
			"3039":{"id":3039,"deep":"1-1.5","dir":"直刺","eff2":"通腑理肠，通络止痛，散结通乳","ill":"小腹痛，泄泻，痢疾，下肢痿痹，乳痈","jl":3,"nam":"下巨虚","team":"腹痛：天枢，气海；下肢麻木：阳陵泉，解溪；乳痈：足三里，梁丘，肩井","xh":"小肠"},
			"3040":{"id":3040,"deep":"1-1.5","dir":"直刺","eff1":"化痰","eff2":"清窍安神，健脾化痰，疏经活络","ill":"头痛，眩晕，癫狂，痰多咳嗽，下肢痿痹，腹胀，便秘","jl":3,"nam":"丰隆","team":"眩晕：风池，脾俞；痰多咳嗽：天突，膻中，肺俞；痫病：神门，太冲；支气管哮喘：内关","xw":"7"},
			"3041":{"id":3041,"deep":"0.5-1","dir":"直刺","eff2":"健脾和胃，镇静宁心，疏经活络","ill":"下肢痿痹，踝关节病，足下垂，头痛，眩晕，癫狂，腹胀，便秘","jl":3,"nam":"解溪","team":"下肢痿痹：阳陵泉，悬钟；腹胀：血海，商丘，足三里","xw":"4"},
			"3042":{"id":3042,"deep":"0.3-0.5","dir":"直刺","ill":"胃痛，口眼?斜，癫狂痫，足委无力","jl":3,"nam":"冲阳","warn":"避开动脉","xw":"6"},
			"3043":{"id":3043,"deep":"0.3-0.5","dir":"直刺","ill":"面目浮肿，水肿，足背肿痛，肠鸣腹痛","jl":3,"nam":"陷谷","xw":"3"},
			"3044":{"id":3044,"deep":"0.5-0.8","dir":"直刺，斜刺","eff2":"清热消肿，健脾和胃，清胃热","ill":"齿痛，咽喉肿痛，口?，鼻衄，热病，胃病吐酸，腹胀，泄泻，痢疾，便秘，足背肿痛","jl":3,"nam":"内庭","team":"齿痛：合谷；口?：地仓，颊车；麦粒肿：点刺放血","xw":"2"},
			"3045":{"id":3045,"deep":"0.1","dir":"浅刺","eff2":"清热消肿，提神苏厥","ill":"鼻衄，齿痛，咽喉肿痛，热病，多梦，癫痫","jl":3,"nam":"厉兑","team":"多梦：内关，神门；中风昏迷：水沟，百会，中冲，大敦","xw":"1"},
			"4001":{"id":4001,"deep":"0.1","dir":"浅刺","eff2":"调经统血，健脾宁心","ill":"月经过多（宜灸），崩漏（宜灸），便血，尿血，癫狂，多梦，惊风，腹胀","jl":4,"nam":"隐白","team":"崩漏：地机，三阴交，阴白；大便下血：足三里","xw":"1"},
			"4002":{"id":4002,"deep":"0.3-0.5","dir":"直刺","ill":"腹胀，胃痛，呕吐，泄泻，便秘，热病","jl":4,"nam":"大都","xw":"2"},
			"4003":{"id":4003,"deep":"0.5-0.8","dir":"直刺","eff2":"健脾和胃，补脾虚，通络止痛，补肺气","ill":"肠鸣，腹胀，泄泻，胃痛，便秘，体重节痛，痔漏","jl":4,"nam":"太白","team":"胃痛：中脘，足三里；便秘：中渚；腹胀食不化：公孙；脾虚泄泻（灸）：太白，丰隆","xw":"36"},
			"4004":{"id":4004,"deep":"0.6-1.2","dir":"直刺","eff2":"健脾和胃（脾虚胃实），镇静安神，调理冲脉","ill":"胃痛，呕吐，腹痛，泄泻，痢疾，心烦失眠，狂病，气上冲心","jh":"冲脉","jl":4,"nam":"公孙","team":"心胸胃病：中脘，内关；胃酸过多，胃痛：梁门，足三里","xw":"79"},
			"4005":{"id":4005,"deep":"0.5-0.8","dir":"直刺","ill":"腹胀，泄泻，便秘，黄疸，足踝痛","jl":4,"nam":"商丘","xw":"4"},
			"4006":{"id":4006,"deep":"1-1.5","dir":"直刺","eff1":"妇科","eff2":"健脾利湿，健脾摄血，治脾不统血，调经助产，宁心安神，调和肝肾，舒筋活络","ill":"肠鸣腹胀，泄泻，月经不调，带下，阴挺，不孕，滞产，遗精，阳痿，遗尿，疝气，失眠，下肢痿痹，脚气","jl":4,"nam":"三阴交","team":"肠鸣泄泻：足三里；月经不调：中极；阴挺：子宫；疝气：大敦；失眠：内关，神门","warn":"孕妇禁针"},
			"4007":{"id":4007,"deep":"1-1.5","dir":"直刺","ill":"腹胀，肠鸣，小便不利，遗精，下肢痿痹","jl":4,"nam":"漏谷"},
			"4008":{"id":4008,"deep":"1-1.5","dir":"直刺","eff2":"调经止崩，健脾利湿，舒筋活络","ill":"月经不调，痛经，崩漏，腹痛，泄泻，小便不利，水肿","jl":4,"nam":"地机","team":"痛经：三阴交，关元；崩漏：隐白","xw":"8"},
			"4009":{"id":4009,"deep":"1-2","dir":"直刺","eff1":"祛湿","eff2":"健脾渗湿，祛脾湿，通利下焦，通络止痛","ill":"腹胀，泄泻，水肿，黄疸，小便不利，失禁，膝痛","jl":4,"nam":"阴陵泉","team":"黄疸：肝俞，至阳；膝痛：透阳陵泉；水肿：水分","xw":"5"},
			"4010":{"id":4010,"deep":"1-1.5","dir":"直刺","eff1":"调经，漏下","eff2":"调经统血，活血，养血，清热凉血","ill":"月经不调，崩漏，经闭，瘾诊，湿疹，丹毒","jl":4,"nam":"血海","team":"月经不调：三阴交；瘾诊：曲池；膝关节疼痛：梁丘，膝阳关，阳陵泉"},
			"4011":{"id":4011,"deep":"0.5-1","dir":"直刺","ill":"小便不利，遗尿，腹股沟肿痛","jl":4,"nam":"箕门","warn":"避开动脉"},
			"4012":{"id":4012,"deep":"0.5-1","dir":"直刺","ill":"腹痛，疝气，崩漏，带下","jl":4,"nam":"冲门","warn":"避开动脉"},
			"4013":{"id":4013,"deep":"1-1.5","dir":"直刺","ill":"腹痛，疝气，积聚","jl":4,"nam":"府舍"},
			"4014":{"id":4014,"deep":"1-2","dir":"直刺","ill":"腹痛，泄泻，疝气","jl":4,"nam":"腹结"},
			"4015":{"id":4015,"deep":"1-2","dir":"直刺","eff2":"通腑理肠","ill":"腹痛，谢谢，便秘，蛔虫症","jl":4,"nam":"大横","team":"腹痛：天枢，足三里；慢性胃痛：脾俞，中脘；肠道蛔虫症：四缝，足三里"},
			"4016":{"id":4016,"deep":"1-1.5","dir":"直刺","ill":"消化不良，腹痛，便秘，痢疾","jl":4,"nam":"腹哀"},
			"4017":{"id":4017,"deep":"0.5-0.8","dir":"斜刺，向外平刺","ill":"胸肋胀痛，噫气，翻胃，腹胀，水肿","jl":4,"nam":"食窦"},
			"4018":{"id":4018,"deep":"0.5-0.8","dir":"斜刺，向外平刺","ill":"胸肋疼痛，咳嗽，乳痛，乳汁少","jl":4,"nam":"天溪"},
			"4019":{"id":4019,"deep":"0.5-0.8","dir":"斜刺，向外平刺","ill":"胸肋胀痛","jl":4,"nam":"胸乡"},
			"4020":{"id":4020,"deep":"0.5-0.8","dir":"斜刺，向外平刺","ill":"咳嗽，气逆，胸肋胀满","jl":4,"nam":"周荣"},
			"4021":{"id":4021,"deep":"0.5-0.8","dir":"斜刺，平刺","eff2":"宽胸理气，养血柔筋","ill":"气喘，胸肋痛，全身疼痛，四肢无力","jl":4,"nam":"大包","team":"四肢无力：足三里","xw":"0"},
			"5001":{"id":5001,"deep":"0.3-0.5","dir":"直刺，斜刺","eff2":"宁心定悸，通络止痛，活血散结","ill":"心痛，心悸，咽干烦渴，肩臂疼痛，胁肋疼痛，瘰疬，腋臭","jl":5,"nam":"极泉","team":"肩臂痛：肩髃，曲池；咽干，咽痛：太渊，天突，偏历；心悸，心痛：神门，内关","warn":"避开腋动脉"},
			"50010":{"id":50010,"jl":0,"nam":"四神聪"},
			"5002":{"id":5002,"deep":"0.5-1","dir":"直刺","ill":"头痛，震寒，肋痛，肩臂疼痛","jl":5,"nam":"青灵"},
			"50020":{"id":50020,"jl":0,"nam":"当阳"},
			"5003":{"id":5003,"deep":"0.5-1","dir":"直刺","eff2":"宁心安神，通络止痛","ill":"心病，癔病，甚至并，肘臂挛痛，头项痛，腋肋痛，瘰疬","jl":5,"nam":"少海","team":"肘臂挛痛：曲池；瘰疬：天井；头痛项强：风池，后溪","xw":"5"},
			"50030":{"id":50030,"ill":"（上）眼睑瞤动","jl":0,"nam":"鱼腰"},
			"5004":{"id":5004,"deep":"0.3-0.5","dir":"直刺","ill":"心痛，暴瘖，肘臂挛痛","jl":5,"nam":"灵道","warn":"不宜深刺以免伤及血管和神经","xw":"4"},
			"50040":{"id":50040,"jl":0,"nam":"上明","no":0},
			"5005":{"id":5005,"deep":"0.3-0.5","dir":"直刺","eff2":"宁心安神，通络止痛，利窍开音","ill":"心悸，怔忡，暴瘖，舌强不语，腕臂痛","jl":5,"nam":"通里","team":"不语：廉泉，哑门；胸痹，心痛：内关，心俞；头痛，目眩：太阳，风池，百会","warn":"不宜深刺以免伤及血管和神经","xw":"7"},
			"50050":{"id":50050,"jl":0,"nam":"太阳"},
			"5006":{"id":5006,"deep":"0.3-0.5","dir":"直刺","eff2":"宁心安神，滋阴清热，凉血固表","ill":"心痛，心烦，骨蒸盗汗，吐血，衄血","jl":5,"nam":"阴郄","team":"心痛：心俞，巨阙；阴虚盗汗：大椎","warn":"不宜深刺以免伤及血管和神经","xw":"8"},
			"50060":{"id":50060,"jl":0,"nam":"耳尖"},
			"5007":{"id":5007,"deep":"0.3-0.5","dir":"直刺","eff2":"补心，宁心安神","ill":"心痛，心烦，惊悸，怔忡，健忘，失眠，癫狂痫，神志病，高血压，胸肋痛","jl":5,"nam":"神门","team":"失眠（心脾血亏：补法，补益心脾=归脾汤）：三阴交；失眠（阴虚火旺：心烦，心事多：泻神门=黄连阿胶汤）：复溜（补）；失眠（心胆气虚：易惊，多梦：补法）：肝俞；失眠（胃中不合）：足三里","xw":"36"},
			"50070":{"id":50070,"jl":0,"nam":"球后"},
			"5008":{"id":5008,"deep":"0.3-0.5","dir":"直刺","ill":"心悸，胸痛，小便不利，遗尿，阴痒痛，小指挛痛","jl":5,"nam":"少府","xw":"2"},
			"50080":{"id":50080,"jl":0,"nam":"上迎香"},
			"5009":{"id":5009,"deep":"0.1","dir":"浅刺，点刺","eff2":"开窍醒神，泻热止痛","ill":"心悸，心痛，癫狂，昏迷，热病，胸肋痛","jl":5,"nam":"少冲","team":"热病，昏迷：太冲，中冲，大椎；小儿惊风：合谷，太冲，水沟；心悸，心痛：内关，心俞","xw":"1"},
			"50090":{"id":50090,"jl":0,"nam":"夹承浆","no":0},
			"50100":{"id":50100,"jl":0,"nam":"内迎香"},
			"50110":{"id":50110,"jl":0,"nam":"聚泉"},
			"50120":{"id":50120,"jl":0,"nam":"海泉"},
			"50130":{"id":50130,"jl":0,"nam":"金津"},
			"50140":{"id":50140,"nam":"玉液"},
			"50150":{"id":50150,"jl":0,"nam":"牵正","no":0},
			"50160":{"id":50160,"jl":0,"nam":"翳明"},
			"50170":{"id":50170,"jl":0,"nam":"安眠","no":0},
			"50180":{"id":50180,"jl":0,"nam":"颈百劳"},
			"50190":{"id":50190,"jl":0,"nam":"提托","no":0},
			"50200":{"id":50200,"jl":0,"nam":"子宫"},
			"50210":{"id":50210,"jl":0,"nam":"三角灸"},
			"50220":{"id":50220,"jl":0,"nam":"定喘"},
			"50230":{"id":50230,"jl":0,"nam":"夹脊"},
			"50240":{"id":50240,"jl":0,"nam":"胃脘下俞"},
			"50250":{"id":50250,"jl":0,"nam":"痞根"},
			"50260":{"id":50260,"jl":0,"nam":"下极俞"},
			"50270":{"id":50270,"jl":0,"nam":"腰眼"},
			"50280":{"id":50280,"jl":0,"nam":"十七椎"},
			"50290":{"id":50290,"jl":0,"nam":"腰奇"},
			"50300":{"id":50300,"jl":0,"nam":"肩前","no":0},
			"50310":{"id":50310,"jl":0,"nam":"肘尖"},
			"50320":{"id":50320,"jl":0,"nam":"臂中","no":0},
			"50330":{"id":50330,"jl":0,"nam":"二白"},
			"50340":{"id":50340,"jl":0,"nam":"中泉"},
			"50350":{"id":50350,"jl":0,"nam":"中魁"},
			"50360":{"id":50360,"jl":0,"nam":"大骨空"},
			"50370":{"id":50370,"jl":0,"nam":"小骨空"},
			"50380":{"id":50380,"jl":0,"nam":"腰痛点"},
			"50390":{"id":50390,"jl":0,"nam":"外劳宫"},
			"50400":{"id":50400,"jl":0,"nam":"八邪"},
			"50410":{"id":50410,"jl":0,"nam":"四缝"},
			"50420":{"id":50420,"jl":0,"nam":"十宣"},
			"50430":{"id":50430,"jl":0,"nam":"环中","no":0},
			"50440":{"id":50440,"jl":0,"nam":"髋骨"},
			"50450":{"id":50450,"jl":0,"nam":"鹤顶"},
			"50460":{"id":50460,"jl":0,"nam":"百虫窝"},
			"50470":{"id":50470,"jl":0,"nam":"膝眼"},
			"50480":{"id":50480,"jl":0,"nam":"胆囊"},
			"50490":{"id":50490,"jl":0,"nam":"阑尾"},
			"50500":{"id":50500,"jl":0,"nam":"内踝尖"},
			"50510":{"id":50510,"jl":0,"nam":"外踝尖"},
			"50520":{"id":50520,"jl":0,"nam":"八风"},
			"50530":{"id":50530,"jl":0,"nam":"独阴"},
			"50540":{"id":50540,"jl":0,"nam":"气端"},
			"6001":{"id":6001,"deep":"0.1","dir":"浅刺，点刺","eff2":"舒筋活血，通乳散结，清热醒神，利咽通窍","ill":"乳痈，乳汁少（向上浅刺），断奶（向下浅刺？），昏迷，热病，头痛，目翳，咽喉肿痛","jl":6,"nam":"少泽","team":"乳汁少，乳痈：膻中，乳根；咽喉肿痛：天容，合谷，尺泽","warn":"孕妇慎用","xw":"1"},
			"6002":{"id":6002,"deep":"0.3-0.5","dir":"直刺","ill":"热病，乳汁少，头痛，目痛，耳鸣，咽喉肿痛","jl":6,"nam":"前谷","xw":"2"},
			"6003":{"id":6003,"deep":"0.5-1","dir":"直刺","eff2":"舒筋活络，清热利窍，安神定志，通督截疟","ill":"头项强痛，腰背痛，落枕，手指及肘臂挛痛，目赤，耳聋，咽喉肿痛，癫狂，疟疾","jh":"督脉","jl":6,"nam":"后溪","team":"项强痛：列缺，悬钟；急性腰扭伤：水沟；腿痛：环跳，阳陵泉","xw":"39"},
			"6004":{"id":6004,"deep":"0.3-0.5","dir":"直刺","eff2":"舒筋活络，聪耳明目，清热退黄，通阳截疟","ill":"指挛腕痛，头项强痛，目翳，耳鸣，黄疸，热病，疟疾","jl":6,"nam":"腕骨","team":"黄疸：阳陵泉，肝俞，胆俞；腿痛：阳陵泉，环跳；颈项强痛：天柱，大杼","xw":"6"},
			"6005":{"id":6005,"deep":"0.3-0.5","dir":"直刺","ill":"颈颌肿，臂外侧痛，腕痛，头痛，目眩，耳鸣耳聋，热病，癫狂痫","jl":6,"nam":"阳谷","xw":"4"},
			"6006":{"id":6006,"deep":"0.5-0.8","dir":"直刺，斜刺","ill":"目视不明，肩背肘臂酸痛","jl":6,"nam":"养老","xw":"8"},
			"6007":{"id":6007,"deep":"0.5-0.8","dir":"直刺，斜刺","eff2":"舒筋活络，清热安神，解毒散疣","ill":"头痛，项强，肘臂酸痛，热病，癫狂，目眩","jl":6,"nam":"支正","team":"头痛：合谷；心痛：内关，神门；肘臂手指麻痛：曲池，肩髃","xw":"7"},
			"6008":{"id":6008,"deep":"0.3-0.5","dir":"直刺","ill":"肘臂疼痛，癫痫","jl":6,"nam":"小海","xw":"5"},
			"6009":{"id":6009,"deep":"1-1.5","dir":"直刺","ill":"肩臂疼痛，瘰疬","jl":6,"nam":"肩贞","warn":"不宜向胸侧深刺"},
			"6010":{"id":6010,"deep":"0.5-1.5","dir":"直刺","ill":"肩臂疼痛，瘰疬","jl":6,"nam":"臑俞","warn":"不宜向胸侧深刺"},
			"6011":{"id":6011,"danger":"3","deep":"0.5-1","dir":"直刺，斜刺","eff2":"舒筋活络，行气宽胸，通乳散结","ill":"肩胛疼痛，气喘，乳痈","jl":6,"nam":"天宗","team":"肩胛痛：肩外俞；乳痈：膻中，足三里","warn":"遇到阻力不可强行进针，肩胛骨最薄弱的地方"},
			"6012":{"id":6012,"deep":"0.5-1","dir":"直刺，斜刺","ill":"肩胛疼痛，气喘，乳痈","jl":6,"nam":"秉风"},
			"6013":{"id":6013,"deep":"0.5-1","dir":"直刺，斜刺","ill":"肩胛疼痛","jl":6,"nam":"曲垣","warn":"不宜向胸侧深刺"},
			"6014":{"id":6014,"deep":"0.5-0.8","dir":"斜刺","ill":"肩背疼痛，颈项强急","jl":6,"nam":"肩外俞","warn":"不宜深刺"},
			"6015":{"id":6015,"deep":"0.5-0.8","dir":"斜刺","ill":"咳嗽，气喘，肩背疼痛","jl":6,"nam":"肩中俞","warn":"不宜深刺"},
			"6016":{"id":6016,"deep":"0.5-1","dir":"直刺","ill":"耳鸣，耳聋，咽喉肿痛，暴瘖，颈项强痛","jl":6,"nam":"天窗"},
			"6017":{"id":6017,"deep":"0.5-1","dir":"直刺","ill":"耳鸣，耳聋，咽喉肿痛，颈项强痛，头痛","jl":6,"nam":"天容","warn":"避开血管"},
			"6018":{"id":6018,"deep":"0.3-0.5，0.5-1","dir":"直刺，斜刺，平刺","eff2":"舒筋活络","ill":"口眼?斜，眼睑瞤动，齿痛，颊肿，三叉神经痛","jl":6,"nam":"颧髎","team":"口?：地仓，颊车；齿痛，三叉神经痛：合谷，颊车，翳风"},
			"6019":{"id":6019,"deep":"1-1.5","dir":"张口直刺","eff2":"聪耳开窍，舒筋活络，安神定志","ill":"耳鸣，耳聋，聤耳，齿痛","jl":6,"nam":"听宫","team":"耳鸣，耳聋：翳风，中渚；齿痛：颊车，合谷，下关","warn":"留针时保持张口姿势"},
			"7001":{"id":7001,"danger":"4","deep":"0.5-1","dir":"直刺","eff2":"清热明目，疏经活络","ill":"目赤肿痛，目眩，近视，急性腰扭伤，心动过速","jl":7,"nam":"睛明","team":"目生翳膜：合谷，四白；目赤：后溪，目窗，瞳子髎；雀目：行间","warn":"患者闭眼，医者左手轻推眼球向外侧固定，右手缓慢进针，紧靠眶缘直刺，不得捻转提插，出针后按压针孔片刻，以防出血"},
			"7002":{"id":7002,"deep":"0.5-0.8，0.2-0.3","dir":"向眉中平刺，斜刺，直刺","eff1":"打嗝","eff2":"疏风止痛，通络明目，宽胸利膈","ill":"头痛，眉棱骨痛，眼睑瞤动，眼睑下垂，目视不明，目赤肿痛，急性腰扭伤，打嗝","jl":7,"nam":"攒竹","team":"头目疼痛：头维；面瘫，面肌痉挛：列缺，颊车"},
			"7003":{"id":7003,"deep":"0.3-0.5","dir":"平刺","ill":"头痛，目眩，鼻塞，鼻衅","jl":7,"nam":"眉冲"},
			"7004":{"id":7004,"deep":"0.3-0.5","dir":"平刺","ill":"头痛，目眩，鼻塞，鼻衅","jl":7,"nam":"曲差"},
			"7005":{"id":7005,"deep":"0.3-0.5","dir":"平刺","ill":"头痛，目眩，癫痫","jl":7,"nam":"五处"},
			"7006":{"id":7006,"deep":"0.3-0.5","dir":"平刺","ill":"头痛，目眩，鼻塞，热病","jl":7,"nam":"承光"},
			"7007":{"id":7007,"deep":"0.3-0.5","dir":"平刺","ill":"头痛，目眩，鼻塞，鼻衅，鼻渊","jl":7,"nam":"通天"},
			"7008":{"id":7008,"deep":"0.3-0.5","dir":"平刺","ill":"头晕，目视不明，耳鸣","jl":7,"nam":"络却"},
			"7009":{"id":7009,"deep":"0.3-0.5","dir":"平刺","ill":"头项痛，目痛，鼻塞","jl":7,"nam":"玉枕"},
			"7010":{"id":7010,"danger":"5","deep":"0.5-0.8","dir":"直刺，斜刺","eff2":"疏经活络，清头明目","ill":"后头痛，项强，肩背腰痛，鼻塞，癫狂痫，热病","jl":7,"nam":"天柱","team":"头项强痛：列缺，后溪；咳嗽：少商","warn":"不可向内伤方深刺，以免伤及延髓"},
			"7011":{"id":7011,"bh":"骨会","deep":"0.5-0.8","dir":"斜刺","ill":"咳嗽，项强，肩背痛","jl":7,"nam":"大杼","warn":"本经背部诸穴不宜深刺，以免伤及内部重要脏器"},
			"7012":{"id":7012,"deep":"0.5-0.8","dir":"斜刺","eff2":"疏风解表，疏经活络","ill":"感冒，咳嗽，发热，头痛，项强，胸背痛","jl":7,"nam":"风门","team":"肩背酸痛：肩井，中渚，委中；咳喘：列缺；外感风寒：风池"},
			"7013":{"id":7013,"bs":"肺","deep":"0.5-0.8","dir":"斜刺","eff2":"宣肺理气，滋阴清热，舒筋活络，祛风止痒","ill":"咳嗽，气喘，咯血，肺气不足，骨蒸潮热，盗汗","jl":7,"nam":"肺俞","team":"风寒咳嗽：列缺，合谷，外关；风热咳嗽：尺泽，曲池，大椎；痰湿咳嗽：肺俞，太渊，丰隆，合谷"},
			"7014":{"id":7014,"bs":"心包","deep":"0.5-0.8","dir":"斜刺","ill":"心痛，心悸，咳嗽，胸闷，呕吐","jl":7,"nam":"厥阴俞"},
			"7015":{"id":7015,"bs":"心","deep":"0.5-0.8","dir":"斜刺","eff2":"宁心安神，宽胸理气，滋阴降火","ill":"心痛，惊悸，失眠，健忘，癫痫，咳嗽，吐血，全身虚弱（宜灸），眼无神（宜灸）","jl":7,"nam":"心俞","team":"心痛：巨阙；失眠健忘：脾俞，神门，足三里，三阴交；癫痫：大椎"},
			"7016":{"id":7016,"deep":"0.5-0.8","dir":"斜刺","ill":"心痛，胸闷，寒热，气喘","jl":7,"nam":"督俞"},
			"7017":{"id":7017,"bh":"血会","deep":"0.5-0.8","dir":"斜刺","eff2":"和胃降逆，养血止血，清热凉血，益气养阴","ill":"所有血症，心绞痛，心肌梗塞，呕吐，呃逆，气喘，吐血，贫血，瘾诊，皮肤瘙痒，潮热，盗汗","jl":7,"nam":"膈俞","team":"心肌梗塞：合谷；血虚：大椎，足三里；胃痛，呃逆：中脘，内关"},
			"7018":{"id":7018,"bs":"肝","deep":"0.5-0.8","dir":"斜刺，直刺","eff2":"疏肝利胆，清肝明目，熄风定志，活血止痉","ill":"黄疸，胸肋胀痛，目疾（直刺1寸），癫狂痫，脊背痛，眉棱骨痛","jl":7,"nam":"肝俞","team":"胁肋疼痛：太冲；健忘，失眠：肾俞，太溪；目昏：光明"},
			"7019":{"id":7019,"bs":"胆","deep":"0.5-0.8","dir":"斜刺，直刺","eff2":"疏肝利胆，养阴补虚","ill":"黄疸，口苦，肋痛，肺痨，潮热","jl":7,"nam":"胆俞","team":"胁肋疼痛：日月；黄疸：公孙，至阳，委中，神门，小肠俞"},
			"7020":{"id":7020,"bs":"脾","deep":"0.5-0.8","dir":"斜刺，直刺","eff2":"健脾利湿，疏经活络","ill":"腹胀，腹泻，呕吐，痢疾，便血，背痛","jl":7,"nam":"脾俞","team":"呕吐：中脘，三阴交，足三里；泄泻：胃俞，中脘，章门，足三里，关元俞；消渴：肾俞，三阴交"},
			"7021":{"id":7021,"bs":"胃","deep":"0.5-0.8","dir":"斜刺，直刺","eff2":"健脾和胃","ill":"胃脘痛，呕吐，腹胀，肠鸣，背痛","jl":7,"nam":"胃俞","team":"胃痛，呕吐：中脘；泄泻：上巨虚"},
			"7022":{"id":7022,"bs":"三焦","deep":"0.5-1","dir":"直刺","ill":"肠鸣，腹胀，腹泻，水肿，腰背强痛","jl":7,"nam":"三焦俞"},
			"7023":{"id":7023,"bs":"肾","deep":"0.5-1","dir":"直刺","eff2":"补肾填精（补肾气，阳虚）","ill":"腰痛，遗尿，遗精，阳痿，月经不调，带下，耳鸣，耳聋，缓解肾结石","jl":7,"nam":"肾俞","team":"滑精：气海，三阴交，志室；月经不调：关元，三阴交，太溪，水泉；五更泄泻：中脘，天枢，足三里"},
			"7024":{"id":7024,"deep":"0.5-1","dir":"直刺","ill":"肠鸣腹胀，痛经，腰痛","jl":7,"nam":"气海俞"},
			"7025":{"id":7025,"bs":"大肠","deep":"0.8-1.2","dir":"直刺","eff2":"疏经活络，通调肠腑","ill":"腰腿痛，腹胀，腹泻，便秘","jl":7,"nam":"大肠俞","team":"腰脊强痛：肾俞，命门，腰阳关，委中；二便不利：小肠俞"},
			"7026":{"id":7026,"deep":"0.8-1","dir":"直刺","ill":"腹胀，腹泻，腰骶痛，尿频，小便不利，遗尿","jl":7,"nam":"关元俞"},
			"7027":{"id":7027,"bs":"小肠","deep":"0.8-1","dir":"直刺","ill":"遗精，遗尿，尿血，尿痛，带下，腹泻，痢疾，腰骶痛","jl":7,"nam":"小肠俞"},
			"7028":{"id":7028,"bs":"膀胱","deep":"0.8-1.2","dir":"直刺，斜刺","eff2":"通调膀胱，疏经活络，清热利湿","ill":"小便不利，遗尿，腰骶痛，腹泻，便秘","jl":7,"nam":"膀胱俞","team":"小便不利：中极，阴陵泉，三阴交，行间"},
			"7029":{"id":7029,"deep":"1-1.5","dir":"直刺","ill":"腹泻，疝气，腰骶痛","jl":7,"nam":"中膂俞"},
			"7030":{"id":7030,"deep":"1-1.5","dir":"直刺","ill":"遗尿，遗精，月经不调，带下，疝气，腰骶痛","jl":7,"nam":"白环俞"},
			"7031":{"id":7031,"deep":"1-1.5","dir":"直刺","ill":"二便不利，月经不调，带下，阴挺，遗精，阳痿，腰骶痛","jl":7,"nam":"上髎"},
			"7032":{"id":7032,"danger":"2","deep":"1-1.5","dir":"直刺","eff2":"通调下焦，疏经活络","ill":"生殖疾病，月经不调，痛经，带下，小便不利，遗精，疝气，腰骶痛，下肢痿痹","jl":7,"nam":"次髎","pos1":"微曲，凸起的软肉之间","team":"月经不调，痛经：三阴交；腰骶痛：委中"},
			"7033":{"id":7033,"deep":"1-1.5","dir":"直刺","ill":"便秘，腹泻，小便不利，月经不调，带下，腰骶痛","jl":7,"nam":"中髎"},
			"7034":{"id":7034,"deep":"1-1.5","dir":"直刺","ill":"腹痛，便秘，小便不利，带下，腰骶痛","jl":7,"nam":"下髎"},
			"7035":{"id":7035,"deep":"1-1.5","dir":"直刺","ill":"痔疾，腹泻，阳痿，带下","jl":7,"nam":"会阳"},
			"7036":{"id":7036,"deep":"1-2","dir":"直刺","ill":"腰骶臀股疼痛，痔疾","jl":7,"nam":"承扶"},
			"7037":{"id":7037,"deep":"1-2","dir":"直刺","ill":"腰痛，下肢痿痹","jl":7,"nam":"殷门"},
			"7038":{"id":7038,"deep":"1-2","dir":"直刺","ill":"股疼痛麻木，腘部疼痛麻木，便秘","jl":7,"nam":"浮郄"},
			"7039":{"id":7039,"deep":"1-1.5","dir":"直刺","eff2":"利水消肿，疏经活络","ill":"腹满，小便不利，腰脊强痛，腿足挛痛","jl":7,"nam":"委阳","team":"腰痛：殷门，阴陵泉，行间；小便淋沥：中极，三阴交，中髎","xh":"三焦"},
			"7040":{
					"id":7040,
					"deep":"1-1.5",
					"dir":"直刺",
					"eff2":"疏经活络，通调肠胃，利水通淋，凉血解毒，清热降火，清头脑热",
					"feel":"4",
					"ill":"腰背痛，下肢痿痹，酸痛，急性吐泻，小便不利，遗尿，丹毒",
					"jl":7,
					"nam":"委中",
					"team":"腰痛：肾俞，阳陵泉，腰阳关，志室，太溪；便血：长强，次髎，上巨虚，承山",
					"warn":"针刺不宜过快，过强，过深，以免损伤血管和神经",
					"xh":"膀胱",
					"xw":"5"
				},
			"7041":{"id":7041,"deep":"0.5-0.8","dir":"斜刺","ill":"颈项强痛，肩背拘急，肘臂麻木","jl":7,"nam":"附分"},
			"7042":{"id":7042,"deep":"0.5-0.8","dir":"斜刺","ill":"咳嗽，气喘，肺痨，项强，肩背痛","jl":7,"nam":"魄户"},
			"7043":{"id":7043,"deep":"0.5-0.8","dir":"斜刺","eff2":"滋阴润肺，疏经活络，补虚益损","ill":"咳嗽，气喘，肺痨，肩胛痛，健忘，盗汗，遗精等虚损诸疾，强身健体（灸）","jl":7,"nam":"膏肓","team":"久咳：肺俞；虚劳：百劳"},
			"7044":{"id":7044,"deep":"0.5-0.8","dir":"斜刺","ill":"咳嗽，气喘，胸闷，脊背强痛","jl":7,"nam":"神堂"},
			"7045":{"id":7045,"deep":"0.5-0.8","dir":"斜刺","ill":"咳嗽，气喘，肩背痛，疟疾，热病","jl":7,"nam":"譩譆"},
			"7046":{"id":7046,"deep":"0.5-0.8","dir":"斜刺","ill":"胸闷，嗳气，呕吐，脊背强痛","jl":7,"nam":"膈关"},
			"7047":{"id":7047,"deep":"0.5-0.8","dir":"斜刺","ill":"胸肋痛，悲痛，呕吐，腹泻","jl":7,"nam":"魂门"},
			"7048":{"id":7048,"deep":"0.5-0.8","dir":"斜刺","ill":"肠鸣，腹痛，腹泻，黄疸，消渴","jl":7,"nam":"阳纲"},
			"7049":{"id":7049,"deep":"0.5-0.8","dir":"斜刺","ill":"腹胀，肠鸣，呕吐","jl":7,"nam":"意舍"},
			"7050":{"id":7050,"deep":"0.5-0.8","dir":"斜刺","ill":"胃脘痛，腹胀，小儿食积，水肿，机悲痛","jl":7,"nam":"胃仓"},
			"7051":{"id":7051,"deep":"0.5-0.8","dir":"斜刺","ill":"腹痛，痞块，便秘，乳疾","jl":7,"nam":"肓门"},
			"7052":{"id":7052,"deep":"0.5-0.8","dir":"斜刺","eff2":"补肾固精，化湿利水，强腰健脊","ill":"遗精，阳痿，小便不利，腰脊强痛","jl":7,"nam":"志室","team":"腰痛：命门，委中；阳痿：肾俞，关元"},
			"7053":{"id":7053,"deep":"1-1.5","dir":"直刺","ill":"肠鸣，腹胀，便秘，癃闭，腰脊强痛","jl":7,"nam":"胞肓"},
			"7054":{"id":7054,"deep":"1.5-2","dir":"直刺","eff2":"疏经活络，通调下焦","ill":"腰骶痛，下肢痿痹，小便不利，便秘，痔疾","jl":7,"nam":"秩边","team":"腰腿痛：殷门，阳陵泉，委中"},
			"7055":{"id":7055,"deep":"1.5-2","dir":"直刺","ill":"腰脊强痛，下肢痿痹，疝气，崩漏","jl":7,"nam":"合阳"},
			"7056":{"id":7056,"ill":"腰腿拒急疼痛，痔疾","jl":7,"nam":"承筋"},
			"7057":{"id":7057,"deep":"1-2","dir":"直刺","eff1":"痔疮","eff2":"疏经活络，通调大肠","ill":"腰腿拒急疼痛，痔疾，便秘","jl":7,"nam":"承山","team":"下肢痿痹：环跳，阳陵泉；痔疾：长强，百会，二白；痔疮：孔最（出血），长强（严重）"},
			"7058":{"id":7058,"deep":"1-1.5","dir":"直刺","eff2":"疏风通窍，活血通络，通调大肠","ill":"头痛，目眩，腰腿疼痛，痔疾","jl":7,"nam":"飞扬","team":"头痛目眩：风池，上星，头维，合谷","xw":"7"},
			"7059":{"id":7059,"deep":"0.8-1.2","dir":"直刺","ill":"腰骶疼痛，下肢痿痹，外踝肿痛，头痛","jl":7,"nam":"跗阳","xw":"a"},
			"7060":{"id":7060,"deep":"0.5-0.8","dir":"直刺","eff2":"疏经活络，息风止痉，转胎催产","ill":"后头痛，项强，腰骶疼痛，足踝肿痛，癫痫，滞产","jl":7,"nam":"昆仑","team":"项强：风池，天柱，肩中俞，后溪；足跟痛：太溪，丘墟，三阴交","warn":"孕妇禁针，经期慎用","xw":"4"},
			"7061":{"id":7061,"deep":"0.3-0.5","dir":"直刺","ill":"下肢痿痹，足跟痛，癫痫","jl":7,"nam":"仆参"},
			"7062":{"id":7062,"deep":"0.3-0.5","dir":"直刺","eff2":"通络清脑，安神定志，强腰健膝","ill":"头痛，眩晕，癫狂痫病，失眠（生物钟紊乱），腰腿酸痛","jh":"阳跷脉","jl":7,"nam":"申脉","team":"癫狂：后溪，前谷；头痛目眩：金门，足三里","xw":"9"},
			"7063":{"id":7063,"deep":"0.3-0.5","dir":"直刺","ill":"头痛，腰痛，下肢痿痹，外踝痛，癫痫，小儿惊风","jl":7,"nam":"金门","xw":"8"},
			"7064":{"id":7064,"deep":"0.3-0.5","dir":"直刺","ill":"头痛，项强，腰痛，癫痫","jl":7,"nam":"京骨","xw":"6"},
			"7065":{"id":7065,"deep":"0.3-0.5","dir":"直刺","eff2":"疏风清热，强腰健膝，镇静安神","ill":"头痛，项强，目眩，腰腿痛，癫狂","jl":7,"nam":"束骨","team":"头痛：风池，百会，印堂，太冲；项强：风池，天柱，后溪；腰腿痛：大肠俞，腰阳关，委中，昆仑","xw":"3"},
			"7066":{"id":7066,"deep":"0.2-0.3","dir":"直刺","ill":"头痛，项强，鼻衄，癫痫","jl":7,"nam":"足通谷","xw":"2"},
			"7067":{"id":7067,"deep":"0.1","dir":"浅刺","eff2":"转胎催产，通窍止痛","ill":"胎位不正（灸），滞产，头痛，目痛，鼻塞，鼻衄","jl":7,"nam":"至阴","team":"胎位不正：艾灸至阴","warn":"胎位不正用灸法","xw":"1"},
			"8001":{"id":8001,"deep":"0.5-1","dir":"直刺","eff2":"醒神开窍，平肝熄风，益肾调便，利咽润肺，滋阴清热","ill":"昏厥，中暑，癫痫，小儿惊风，头痛，头晕，咯血，咽喉肿痛，小便不利，便秘，足心热，奔豚气","jl":8,"nam":"涌泉","team":"昏厥：水沟，内关；小儿惊风：前顶，印堂，神门；咽喉肿痛：太溪，照海，鱼际","warn":"防止刺伤足底动脉弓","xw":"1"},
			"8002":{"id":8002,"deep":"0.5-1","dir":"直刺","eff1":"降血糖（配胰俞）","eff2":"益肾调经，温阳固精，清热利湿，疏经活络","ill":"月经不调，带下，阴挺，遗精，阳痿，小便不利，咯血，咽喉肿痛，消渴，小儿脐风，口噤不开，下肢痿痹，足跗痛","jl":8,"nam":"然谷","team":"月经不调：肾俞，太溪，关元，三阴交；遗精：肾俞，志室，气海；阴痒：中极，血海，蠡沟，三阴交","xw":"2"},
			"8003":{"id":8003,"deep":"0.5-1","dir":"直刺","eff2":"补肾益气（补肾气，滋肾阴），滋阴利窍，益肾纳气，通调二便，温阳散寒","ill":"头痛，目眩，咽喉肿痛，齿痛，耳聋，耳鸣，月经不调，遗精，阳痿，小便频数，腰脊痛，下肢厥冷，内踝肿痛，气喘，胸痛，咯血，消渴，失眠，健忘","jl":8,"nam":"太溪","team":"失眠：大陵，神门，少冲，志室；咯血：尺泽，鱼际，孔最；滑精：气海，三阴交，志室","xw":"36"},
			"8004":{"id":8004,"deep":"0.5-1","dir":"直刺","eff2":"益肾利水，止咳平喘，调神益智，通络止痛","ill":"癃闭，遗尿，月经不调，腰脊强痛，足跟痛，气喘，咯血","jl":8,"nam":"大钟","team":"咯血：孔最，尺泽，鱼际；月经不调：肾俞，关元，三阴交；腰脊强痛：肾俞，太溪，委中","xw":"7"},
			"8005":{"id":8005,"deep":"0.3-0.5","dir":"直刺","ill":"月经不调，痛经，小便不利","jl":8,"nam":"水泉","xw":"8"},
			"8006":{"id":8006,"deep":"0.5-1","dir":"直刺","eff2":"滋阴调经，宁心安神，清热利咽，通调二便","ill":"痫病，失眠，咽干咽痛，目赤肿痛，小便不利，尿频，月经不调，痛经，赤白带下，下肢痿痹","jh":"阴跷脉","jl":8,"nam":"照海","team":"咽喉肿痛（过敏例外）：列缺，照海，天突；癃闭：中极，三阴交；月经不调：肾俞，关元，三阴交","xw":"9"},
			"8007":{"id":8007,"deep":"0.5-1","dir":"直刺","eff2":"补肾利水（滋肾阴），敛阴止汗，疏经活络","ill":"水肿，腹胀，盗汗，身热无汗，肠鸣，泄泻，足痿，强脊强痛","jl":8,"nam":"复溜","team":"泄泻：肾俞，关元，天枢，足三里；水肿：肾俞，脾俞，太溪，足三里；汗出不止：合谷","xw":"4"},
			"8008":{"id":8008,"deep":"0.5-1","dir":"直刺","ill":"月经不调，痛经，崩漏，腹痛，腹泻，小便不利，水肿，睾丸肿痛，疝气，膝内侧痛，股内侧痛，腘内侧痛","jl":8,"nam":"交信","xw":"b"},
			"8009":{"id":8009,"deep":"1-1.5","dir":"直刺","ill":"癫狂痫病，呕吐，疝气，小腿内侧痛","jl":8,"nam":"筑宾","xw":"c"},
			"8010":{"id":8010,"deep":"1-1.5","dir":"直刺","ill":"阳痿，疝气，月经不调，崩漏，小编男，膝内侧痛，股内侧痛","jl":8,"nam":"阴谷","xw":"5"},
			"8011":{"id":8011,"deep":"1-1.5","dir":"直刺","ill":"小腹胀痛，疝气，小便不利，遗尿，遗精，阳痿","jl":8,"nam":"横骨"},
			"8012":{"id":8012,"deep":"1-1.5","dir":"直刺","ill":"月经不调，痛经，带下，遗精，阳痿","jl":8,"nam":"大赫"},
			"8013":{"id":8013,"deep":"1-1.5","dir":"直刺","ill":"月经不调，带下，小便不利，泄泻","jl":8,"nam":"气穴"},
			"8014":{"id":8014,"deep":"1-1.5","dir":"直刺","ill":"腹痛，疝气，便秘，月经不调，带下，遗尿，遗精","jl":8,"nam":"四满"},
			"8015":{"id":8015,"deep":"1-1.5","dir":"直刺","ill":"腹痛，便秘，泄泻，月经不调","jl":8,"nam":"中注"},
			"8016":{"id":8016,"deep":"1-1.5","dir":"直刺","ill":"腹痛，泄泻，便秘","jl":8,"nam":"肓俞"},
			"8017":{"id":8017,"deep":"0.5-0.8","dir":"直刺","ill":"噫气，反胃，腹胀，水肿，胸肋胀痛","jl":8,"nam":"商曲"},
			"8018":{"id":8018,"deep":"1-1.5","dir":"直刺","ill":"呕吐，腹痛，便秘，不孕","jl":8,"nam":"石关"},
			"8019":{"id":8019,"deep":"1-1.5","dir":"直刺","ill":"腹胀，腹泻，便秘，不孕","jl":8,"nam":"阴都"},
			"8020":{"id":8020,"deep":"0.5-0.8","dir":"直刺","ill":"腹痛，腹胀，呕吐","jl":8,"nam":"腹通谷"},
			"8021":{"id":8021,"deep":"0.5-0.8","dir":"直刺","ill":"腹痛，腹胀，呕吐，泄泻","jl":8,"nam":"幽门","warn":"不可向上深刺，以免损伤内脏"},
			"8022":{"id":8022,"deep":"0.5-0.8","dir":"斜刺，平刺","ill":"胸痛，咳嗽，气喘，乳痈，呕吐不嗜食","jl":8,"nam":"步廊"},
			"8023":{"id":8023,"deep":"0.5-0.8","dir":"斜刺，平刺","ill":"咳嗽，气喘，胸肋支满，乳痈，呕吐不嗜食","jl":8,"nam":"神封"},
			"8024":{"id":8024,"deep":"0.5-0.8","dir":"斜刺，平刺","ill":"咳嗽，气喘，痰多，胸肋胀痛，乳痈，呕吐","jl":8,"nam":"灵墟"},
			"8025":{"id":8025,"deep":"0.5-0.8","dir":"斜刺，平刺","ill":"咳嗽，气喘，胸痛，烦满，呕吐，不嗜食","jl":8,"nam":"神藏"},
			"8026":{"id":8026,"deep":"0.5-0.8","dir":"斜刺，平刺","ill":"咳嗽，气喘，胸肋胀满，不嗜食","jl":8,"nam":"彧中"},
			"8027":{"id":8027,"deep":"0.5-0.8","dir":"斜刺，平刺","eff2":"宽胸理气","ill":"咳嗽，气喘，胸痛，不嗜食","jl":8,"nam":"俞府","team":"咳嗽多痰：肺俞，膻中，丰隆；呕吐：天突"},
			"9001":{"id":9001,"deep":"0.5-0.8","dir":"斜刺，平刺","eff2":"宽胸理气，散结通乳，化痰散瘀","ill":"乳痈，乳少，咳嗽，气喘，胸肋疼痛","jl":9,"nam":"天池","team":"乳痈，乳少：膻中，乳根，少泽；腋窝淋巴结炎：委阳，极泉","warn":"不可深刺，以免损伤内脏"},
			"9002":{"id":9002,"deep":"0.5-0.8","dir":"直刺","ill":"咳嗽，胸胁胀痛，胸背及上臂内侧痛","jl":9,"nam":"天泉"},
			"9003":{"id":9003,"deep":"0.8-1","dir":"直刺，点刺出血","eff2":"宁心止痛，和中降逆，运脾止泻，清心泄热，疏经活络，清上焦之热","ill":"心痛，心悸，胃痛，呕吐，泄泻，肘臂挛痛，热病","jl":9,"nam":"曲泽","team":"呕吐：内关，中脘；中暑：委中，曲池","xw":"5"},
			"9004":{"id":9004,"jl":9,"nam":"郄门","xw":"8"},
			"9005":{"id":9005,"deep":"0.5-1","dir":"直刺","eff2":"宽胸止痛，和胃降逆，泄热截疟，宁心安神，疏经止痛","ill":"心痛，心悸，癫狂痫，胃痛，呕吐，热病，疟疾，臂痛，情志病（全身性的，偏行气上滞，气滞，脉弱引起的病）","jl":9,"nam":"间使","team":"心悸：心俞；癫狂：后溪，合谷；胃痛：内关，胃俞，中脘；全身性气滞：三阴交","xw":"4"},
			"9006":{"id":9006,"deep":"0.5-1","dir":"直刺","eff2":"宽胸理气，和胃止呕，疏经止痛，宁心安神，通畅心胸","ill":"心痛，心悸，胸闷，胸痛，胃痛，呕吐，呃逆，失眠，癫狂，上肢疼痛，偏瘫，手指麻木，情志病（偏心胸引起的）","jh":"阴维脉","jl":9,"nam":"内关","team":"神志病：神门；失眠：大陵，神门；心痛：郄门；胃痛，呕吐（拉肚子+公孙）：足三里，中脘；","xw":"79"},
			"9007":{"id":9007,"deep":"0.3-0.5","dir":"直刺","eff2":"宽胸理气，和胃降逆，宁心安神，疏经止痛","eff3":"不如内关，神门","ill":"心痛，心悸，胸肋痛，癫狂，胃痛，呕吐，腕臂痛","jl":9,"nam":"大陵","team":"心悸：心俞，巨阙，间使，神门；心胸痛：曲泽，内关；胃痛：内关，公孙，足三里，中脘","xw":"36"},
			"9008":{"id":9008,"deep":"0.5-0.5","dir":"直刺","eff2":"醒神开窍，宽胸理气，清心泻火，祛风止痒","ill":"心痛，心悸，癫狂痫，口痔，口臭","jl":9,"nam":"劳宫","team":"昏迷中暑：水沟，十宣，曲泽，委中；口痔，口臭：金津，玉液，内庭","warn":"较痛，年老体弱孕妇慎用","xw":"2"},
			"9009":{"id":9009,"deep":"0.1","dir":"浅刺，点刺出血","eff2":"醒神开窍，清心泄热","ill":"昏迷，中暑，昏厥，心痛，小儿夜啼，舌强肿痛，中风急救","jl":9,"nam":"中冲","team":"中风昏迷，舌强不语：水沟，太冲，劳宫，曲泽；中暑：大椎，曲池，曲泽","xw":"1"}
		},
	"gdIllness":{
			"1":{"id":1,"aupnam":"暴?","content":"?："},
			"10":{"id":10,"aupnam":"癃闭","content":"癃闭，中医病名。又称小便不通；尿闭。以小便量少，点滴而出，甚则闭塞不通为主症的一种疾患。病情轻者涓滴不利为癃，重者点滴皆无称为闭。癃闭有虚实之分，实证多因湿热、气结、瘀血阻碍气化运行；虚证多因中气，肾阳亏虚而气化不行。临床多因败精阻塞、阴部手术等，使膀胱气化失司，水道不利，以小便量少、点滴而出、甚至闭塞不通。属肾病和排尿障碍。现代医学称为尿潴留。"},
			"11":{"id":11,"aupnam":"痢疾","content":"痢疾，中医病证名。是以痢下赤白脓血，腹痛，里急后重为临床特征。主要病因是外感时邪疫毒，内伤饮食不洁。病位在肠，与脾胃有密切关系。病机为湿热、疫毒、寒湿结于肠腑，气血壅滞，脂膜血络受损，化为脓血，大肠传导失司，发为痢疾。暴痢多实证，久痢多虚证。痢疾的治疗，以初痢宜通，久痢宜涩，热痢宜清，寒痢宜温，寒热虚实夹杂者宜通涩兼施、温清并用。对具传染性的细菌性痢疾和阿米巴痢疾，应重在预防，控制传染。"},
			"12":{"id":12,"aupnam":"翻胃","content":"翻胃主要有有两种意思。。①即反胃。亦称胃反。见《肘后备急方》卷四。详见反胃、胃反条。指食物咽下后胃里不舒服，有恶心甚至呕吐的症状。另一种称反刍。指某些动物先将食物吃进胃里，然后返回嘴里咀嚼，再咽下消化的生理现象。②指大便溏利，每食必吐之膈症。《医宗己任篇·膈症》：“有一种大便甚利且溏，每食必吐，是名翻胃。王太仆云：食入反出，是无火也，八味丸主之。此验症全在大便，如一干结，便非无火。一味滋润如前法。”"},
			"13":{"id":13,"aupnam":"目翳","content":"从中医上讲分为风热型、肝肾阴虚型、气血郁滞型。风热型本型因外感风伤卫表，循经上犯目系，则目翳大小不等，厚薄不一，遮盖瞳孔，伴有视力模糊或视力障碍，头痛，或发热，苔黄白相兼，脉弦数。肝肾阴虚型本型肾水不足，则目失润养，以致目涩弱视、腰痛、耳鸣，或眩晕、视力障碍、形体消瘦，舌质红、苔少，脉弦细。气血郁滞型本型因气血郁滞，结聚目系，则因重大的精神刺激或外伤，目翳遮瞳，视力困难，每多叹息，胁痛易怒，头痛目胀，舌质暗有瘀斑，脉弦涩。"},
			"14":{"id":14,"aupnam":"聤耳","content":"一般指中耳炎，发生于中耳部的急性或慢性化脓性耳病。其特征是急性发作者，初起耳内瘙痒，继而暴肿赤热，剧烈跳痛，耳窍流脓，伴有怕冷、发热等全身症状；慢性发作者，初起耳内胀痛，继而耳窍流脓，疼痛减轻，有全身不适，发热等症状。因有耳窍流脓，所以又叫耳脓。相当于西医的化脓性中耳炎。治疗以清肝火，化湿热为原则。","nownam":"中耳炎"},
			"15":{"id":15,"aupnam":"升提","content":"升提为治法名，是对气陷证的治疗。气陷指气的上升不足或下降太过，以气虚升举无力而下陷为特征的一种病理状态。气陷多由气虚病变发展而来，尤与脾气的关系最为密切。若素体虚弱，或病久耗伤，致脾气虚损，清阳不升，或中气下陷，从而形成气虚下陷的病变。气陷的病理变化，主要有“上气不足”与“中气下陷”两方面。升提法是运用具有生发清气作用的中药结合其他药物，来治疗气机的下陷，古籍中运用生提治疗疾病的方法有很多，比如升提中气治脾虚下陷，升提大气治胸闷怔忡，《伤寒论》中更有利用升提治法疗下利的详细记述等等。"},
			"16":{"id":16,"aupnam":"噫气","content":"噫气乃口反食气之病。又名嗳气，为胃中之浊气上逆，经食道而由口排出之气体。是脾胃疾病之一。《灵枢。口问篇》曰；“寒气客于胃，逆从下上散，复出于胃，故谓噫”。"},
			"17":{"id":17,"aupnam":"怔忡","content":"怔忡，为病名，首见于《济生方·惊悸怔忡健忘门》中“惊者，心卒动而不宁也；悸者,心跳动而怕惊也；怔忡者，心中躁动不安，惕惕然后人将捕之也”,是心悸的一种，是指多因久病体虚、心脏受损导致气血、阴阳亏虚，或邪毒、痰饮、瘀血阻滞心脉，日久导致心失濡养，心脉不畅，从而引起的心中剔剔不安，不能自控的一种病证，常和惊悸合并称为心悸。"},
			"18":{"id":18,"aupnam":"雀目","content":"雀目，病证名。系指夜间视物不清的一类病证。又有鸡蒙眼、鸡盲等别称。亦即今之夜盲。"},
			"19":{"id":19,"aupnam":"目生翳膜","content":"白内障"},
			"2":{"id":2,"aupnam":"瘿气","content":"中医病症之一。是以颈部长包块，不与皮肤粘连，触之光滑或有结节为主要证候的一种疾病。各种年龄均可患此病，尤其多见于青、壮年女性。瘿气多由情志抑郁，气结不化，津液凝聚成痰，气滞血瘀，气、痰、瘀三者互结于颈部而成，或由外感六淫之邪，山岗沙水病气侵犯，或水土不宜，均可导致气血郁滞，经络阻塞而成本病。民间多用灸法治疗。"},
			"20":{"id":20,"aupnam":"痞块","content":"痞块，指肚子里可以摸得到的硬块，是脾脏肿大引起的，也叫“痞积”。伤寒病、败血病、慢性疟疾、黑热病等都会发生这种症状。"},
			"21":{"id":21,"aupnam":"奔豚气","content":"奔豚气属内科病证，是指患者自觉有气从少腹上冲胸咽的一种病证。由于气冲如豚之奔突，故名奔豚气。病名，见《金匮要略·奔豚气病脉证治》。亦称奔豚、贲豚、贲豚气。可见于现代医学的神经官能症、冠心病等有类似症状者。"},
			"22":{"id":22,"aupnam":"胞衣不下","content":"胞衣不下是一个病症，即产妇娩出胎儿后，经过半小时，胞衣（胎盘）仍不能自动排出的病症。多由分娩后元气大虚而无力排出胞衣，或产时感受外寒而气血凝滞所致，大多伴有出血症状。"},
			"23":{"id":23,"aupnam":"阴挺","content":"妇女子宫下脱，甚则脱出阴户之外，或者阴道壁膨出，称为阴挺，又称阴脱、阴菌、阴痔、产肠不收、葫芦颓等。多由分娩损伤所致，常见于经产妇。现代医学分别称为“子宫脱垂”、“阴道壁膨出”。明代张景岳《景岳全书·妇人规》中云：“此或因胞络伤损，或因分娩过劳，或因郁热下坠，或因气虚下脱，大都此证”，应该以升补元气、固涩真阴为治疗原则。","nownam":"子宫脱垂，阴道壁膨出"},
			"3":{"id":3,"aupnam":"瘰疬","content":"淋巴结核,瘰疬又称老鼠疮，生于颈部的一种感染性外科疾病。在颈部皮肉间可扪及大小不等的核块，互相串连，其中小者称瘰，大者称疬，统称瘰疬，俗称疬子颈。多见于青少年及原有结核病者，好发于颈部、耳后，也有的缠绕颈项，延及锁骨上窝、胸部和腋下。相当于现代医学的淋巴结核，多是由于结核杆菌侵入颈部所引起的特异性感染，严重时可溃破流脓。该病早期并无明显症状，病情发展后可有全身症状如疲乏、食欲不振、消瘦、低热等，还有病变器官的局部症状。"},
			"4":{"id":4,"aupnam":"鼽衄","content":"拼音是qiú nǜ，意思是指鼻流清涕或鼻腔出血的病证"},
			"5":{"id":5,"aupnam":"疔疮","content":"疔疮是好发于颜面和手足部的外科疾患。本病开始有粟米样小脓头，发病迅速，根深坚硬如钉为特征。因发病部位和形状不同，而有“人中疔”、“虎口疔”、“红丝疔”等名称。现代医学的“疖”属本病范畴。疔疮初起切忌挤压、挑刺，患部不宜针刺，红肿发硬时忌手术切开，以免引起感染扩散。疔疮走黄症情凶险，须及时抢救，疔疮如已成脓，应施行外科处理。"},
			"6":{"id":6,"aupnam":"暴瘖","content":"喉瘖，中医病证。以声音不扬、嘶哑甚至失音为主要表现的喉病。其发病急、病程短为急喉瘖，又称暴瘖，与西医的急性喉炎类似。久病声音嘶哑为慢喉瘖，又称久瘖，与西医的慢性喉炎类似。急喉瘖多因感受风热邪毒，风火热毒蕴结于喉，经脉阻塞；或风寒外袭，寒邪凝聚于喉，脉络阻滞等引起。"},
			"7":{"id":7,"aupnam":"泄泻","content":"泄泻是指因感受外邪，或被饮食所伤，或情志失调，或脾胃虚弱，或脾肾阳虚等原因引起的以排便次数增多，粪便稀溏，甚至泄如水样为主证的病证。一般根据病因病机运用淡渗，升提，清凉，疏利，甘缓，酸收，燥脾，温肾，固涩的方法治疗。"},
			"8":{"id":8,"aupnam":"带下","content":"中医的“带下”有广义和狭义之分，广义泛指妇科疾病，狭义则专指白带的量色质气味发生异常的疾病。正常白带由前庭大腺分泌物、阴道黏膜渗出物、宫颈及子宫内膜腺体分泌物等混合形成白带。正常白带呈白色黏液状或蛋清样，量少，无异味，称生理性白带。白带的量明显增多，色、质、气味发生异常，或伴全身、局部症状者，称为“带下病”，又称“下白物”、“流秽物”。造成白带异常，也就是病理性白带的原因很多，多数白带异常为感染或炎症引起，如滴虫性阴道炎、霉菌性阴道炎、老年性阴道炎、子宫颈糜烂、子宫内膜炎、也有部分由于宫内节育器、子宫颈息肉、宫颈癌等其他疾病引起。临床表现常见白带增多、绵绵不断、腰痛、神疲等，或见赤白相兼，或五色杂下，或脓浊样，有臭气等。"},
			"9":{"id":9,"aupnam":"鼻渊","content":"鼻渊，中医病名。是指鼻流浊涕，如泉下渗，量多不止为主要特征的鼻病。常伴头痛、鼻塞、嗅觉减退，鼻窦区疼痛，久则虚眩不已。是鼻科常见病、多发病之一。亦有“脑漏”、“脑砂”、“脑崩”、“脑渊”之称。多因外感风热邪毒，或风寒侵袭，久而化热，邪热循经上蒸，犯及鼻窍；或胆经炎热，随经上犯，蒸灼鼻窍；或脾胃湿热，循胃经上扰等引起。"}
		},
	"gdMeridian":{
			"0":{"id":0,"nam":"经外奇穴"},
			"1":{"id":1,"food":"白菜、梨子、豆腐、豆浆、牛奶。","nam":"手太阴肺经","shi":"呼吸不畅、咽喉异常、胸闷、气喘、扁桃炎、咳嗽、肩背酸痛易患痔疮等 ","time":"凌晨3点-5点（寅时）是肺经开穴运行的时间。寅时肺经旺，寅时睡得熟，色红精气足。 “肺朝百脉。”肝在丑时把血液推陈出新之后，将新鲜血液提供给肺，通过肺送往全身。所以，人在清晨面色红润，精力充沛。寅时，有肺病者反映最为强烈，如剧咳或哮喘而醒。 ","treat":"主治喉、胸、肺病，以及经脉循行部位的其他病证。如咳嗽，气喘，少气不足以息，咳血，伤风，胸部胀满，咽喉肿痛，缺盆部及手臂内侧前缘痛，肩背寒冷、疼痛等证。","xu":"皮肤免疫力下降，天寒手足冰冷、麻痹、咽喉干、咳嗽等。 "},
			"10":{"id":10,"nam":"手少阳三焦经","shi":"淋巴发炎、偏头痛、肩膀酸痛、颈侧酸痛无力、发热、耳鸣、小便异常等。","time":"亥时（21点到23点）－－三焦经旺。亥时百脉通，养身养娇容。 三焦是六腑中最大的腑，具有主持诸气，疏通水道的作用。亥时三焦能通百脉。人如果在亥时睡眠，百脉可得到最好的休养生息，对身体对美容十分有益。百岁老人有个共同特点，即在亥时睡觉。现代人如不想此时睡觉，可听音乐、看书、看电视、练瑜伽，但最好不要超过亥时睡觉。 ","treat":"主治侧头、耳、目、胸胁、咽喉病，热病以及经脉循行部位的其他病证。如腹胀，水肿，遗尿，小便不利，耳鸣，耳聋，咽喉肿痛，目赤肿痛，颊肿，耳后、肩臂肘部外侧疼痛等证。","xu":"免疫力下降、易疲劳、上肢无力、腹部堵胀、体毛变浓、呼吸困难、胃寒等。 "},
			"11":{"id":11,"nam":"足少阳胆经","time":"子时（23点至1点）—胆经旺。子时睡得足，黑眼圈不露； 中医理论认为；“肝之余气，泄于明胆，聚而成精。”人在子时前入眠，胆方能完成代谢。“胆汁有多清，脑就有多清。”子时前入睡者，晨醒后头脑清晰、气色红润，没有黑眼圈。反之，常于子时内不能入睡者，则气色青白，眼眶昏黑。同时因胆汁排毒代谢不良更容易生成结晶、结石。","treat":"主治侧头、目、耳、咽喉病，神志病，热病以及经脉循行部位的其他病证。如口苦，目眩，疟疾，头痛，颔痛，目外眦痛，缺盆部肿痛，腋下肿，胸、胁、股及下肢外侧痛，足外侧痛，足外侧发热等证。"},
			"12":{"id":12,"food":"花生、芝麻、核桃仁、山楂、葡萄、香蕉、李子、番茄、莲藕、韭菜、木耳、牛肉、鸡肉、海带等。 ","nam":"足厥阴肝经","shi":"肝火旺、脾气不好、头晕腰痛、月经失调、失眠、肋间神经痛等。 ","time":"凌晨1点-3点（丑时）是肝经开穴运转排毒的时间，丑时肝经旺。丑时不睡晚，脸上不长斑； 中医理论认为：“肝藏血。”“人卧则血归于肝。”如果丑时不能入睡，肝脏还在输出能量支持人的思维和行动，就无法完成新陈代谢。所以丑时前未能入睡者，面色青灰，情志怠慢而躁，易生肝病，脸色晦暗长斑。 ","treat":"主治肝病，妇科、前阴病以及经脉循行部位的其他病证。如腰痛，胸满，呃逆，遗尿，小便不利，疝气，少腹肿等证。","xu":"易疲劳、视力减退、性功能减退、头晕眼花、皮肤枯黄等。 "},
			"13":{"id":13,"nam":"督脉"},
			"14":{"id":14,"nam":"任脉"},
			"15":{"id":15,"nam":"冲脉"},
			"16":{"id":16,"nam":"带脉"},
			"17":{"id":17,"nam":"阴跷脉"},
			"18":{"id":18,"nam":"阳跷脉"},
			"19":{"id":19,"nam":"阴维脉"},
			"2":{"id":2,"food":"茄子、菠菜、香蕉、蘑菇、木耳、玉米、扁豆、豌豆等。","nam":"手太阳大肠经","shi":"腹胀、易便秘、易患痔疮、肩背部不适或疼痛、牙疼、皮肤异常、上脘异常等。 ","time":"凌晨5点-7点（卯时）这段时间是手阳明大肠经开穴运行的时间 卯时大肠经旺，卯时大肠蠕，排毒渣滓出； “肺与大肠相表里。”肺将充足的新鲜血液布满全身，紧接着促进大肠进入兴奋状态，完成吸收食物中的水分和营养、排出渣滓的过程。清晨起床后最好排大便。 ","treat":"主治头面、五官疾患，热病，皮肤病，肠胃病，神智病及经脉循行部位的其他病证。如腹痛，腹鸣腹泻、大肠功能减弱、肩膀僵硬、皮肤无光泽、肩酸、喉干、喘息、宿便，腹胀、易便秘、易患痔疮、肩背部不适或疼痛、牙疼、皮肤异常、上脘异常等。","xu":"腹痛，腹鸣腹泻、大肠功能减弱、肩膀僵硬、皮肤无光泽、肩酸、喉干、喘息、宿便等。 "},
			"20":{"id":20,"nam":"阳维脉"},
			"3":{"id":3,"food":"凤梨、香瓜、南瓜、番茄、柠檬、柳橙、苹果、红茶、茴香、芹菜、木耳、香菜、蘑菇、玉米、牛肉、牛奶、羊奶、扁豆、马铃薯等。","nam":"足阳明胃经","shi":"容易饿、胃弱、关节异常、食欲异常、口干、易便秘 。","time":"辰时（7点到9点）—胃经旺。辰时吃早餐，营养身体安； 7点-9点这时大部分人都已经起床了，如果你有胃痛、胃酸等毛病，可以建议在这个时间段养养胃哦，因为这段时间是胃经开穴运行的时间，在这个时间段来吃些养胃的食物效果是最明显的。起床健身后，饮一杯白开水，用木梳梳发百余遍，有醒脑明目的作用。洗脸漱口，早餐。早餐宜食粥，宜淡素，宜饱。","treat":"主治胃肠病、头面、目、鼻、口、齿痛、神志病及经脉循行部位的其他病证。如肠鸣腹胀，水肿，胃痛，呕吐或消谷善饥，口渴，咽喉肿痛，鼻衄，胸部及膝膑等本经循行部位疼痛，热病，发狂等病证。","xu":"消化不良、易胃胀气和食欲不振、颜面浮肿、易打嗝、饭后容易胃痛、腹泻或呕吐。 "},
			"4":{"id":4,"nam":"足太阴脾经","shi":"脾胃不和消化吸收不好、易腹胀气打嗝、头疼、疲倦乏力、膝关节异常、排便异常等。","time":"已时（9点至11点）—脾经旺。已时脾经旺，造血身体状； “脾主运化，脾统血。”脾是消化、吸收、排泄的总调度，又是人体血液的统领。“脾开窍于口，其华在唇。”脾的功能好，消化吸收好，血液质量好，所以嘴唇是红润的。唇白标志血气不足，唇暗、唇紫标志寒入脾经。","treat":"主治脾胃病，妇科，前阴病及经脉循行部位的其他病证。如胃脘痛，食则呕，嗳气，腹胀便溏，黄疸，身重无力，舌根强痛，下肢内侧肿胀，厥冷等","xu":"内分泌失调或分泌不足、胃弱、膝异常、易失眠、疲劳、食欲不振、大便异常、腹胀等。 "},
			"5":{"id":5,"nam":"手少阴心经","shi":"呼吸不畅血液循环不良引起的头痛、口干口苦、掌心发热等。","time":"午时（11点至13点）—心经旺。午时一小憩，安神养精气； “心主神明，开窍于舌，其华在面。”心气推动血液运行，养神、养气、养筋。我们饭后都想睡一会，但是由于种种原因克制了这种欲望，如果有条件只要稍微的睡10分钟也会对我们的心脏有很大的帮助，也不要担心会发胖因为时间很短，还可以帮助肠胃蠕动减少负担。午餐应美食，不是指山珍海味，而是要求食物暖软，不要吃生冷坚硬的食物。只吃八分饱。食后用茶漱口，涤去油腻，然后午休。 ","treat":"主治心、胸、神志病以及经脉循行部位的其他病证。如心痛，咽干，口渴，目黄，胁痛，上臂内侧痛，手心发热等。","xu":"胸闷、脸发红、四肢沉重、易疲倦、气血不良、胸痛、心悸亢奋、语言障碍等。 "},
			"6":{"id":6,"nam":"手太阳小肠经","time":"未时（13点到15点）—小肠经旺。未时分清浊，饮水能降火； 小肠分清浊，把水液归于膀胱，糟粕送入大肠，精华上输于脾。小肠经在未时对人一天的营养进行调整。如小肠有热，人会干咳、排屁。此时多喝水、喝茶有利小肠排素降火。","treat":"主治头、项、耳、目、咽喉病，热病，神经病以及经脉循行部位的其他病证。如少腹痛，腰脊痛引睾丸，耳聋，目黄，颊肿，咽喉肿痛，肩臂外侧后缘痛等。"},
			"7":{"id":7,"nam":"足太阳膀胱经","shi":"后颈部疼痛、坐骨神经痛、腰痛、头疼、流泪、流鼻血等。","time":"申时（15点至17点）—膀胱经旺。申时津液足，养阴身体舒； 膀胱贮藏水液和津液，水液排出体外，津液循环在体内。若膀胱有热可致膀胱咳，且咳而遗尿。申时人体温较热，阴虚的人最为突出。此时适当的活动有助于体内津液循环，喝滋阴泻火的茶水对阴虚的人最有效。 ","treat":"主治头、项、目、背、腰、下肢部病证以及神志病，背部第一侧线的背俞穴及第二侧线相平的腧穴，主治与其相关的脏腑病证和有关的组织器官病证。如小便不通，遗尿，癫狂，疟疾，目痛，迎风流泪，鼻塞多涕，鼻血丑，头痛，项、背、腰、臀部以及下肢后侧本经循行部位疼痛等证。","xu":"背部异常、腰痛、脚神经异常、腿酸、痔疮尿频等。 "},
			"8":{"id":8,"nam":"足少阴肾经","shi":"耳鸣、月经不调、口干舌燥、血压异常、小便量少、色深、浑浊、性欲减退、神经衰弱、足发热发汗、生殖器病变等。","time":"酉时（17点至19点）—肾经旺。酉时肾藏精，纳华元气清； “肾藏生殖之精和五脏六腑之精。肾为先天之根。”人体经过申时泻火排毒，肾在酉时进入贮藏精华的阶段。此时不适宜太强的运动量，也不适宜大量喝水。 ","treat":"主治妇科，前阴病，肾、肺、咽喉病及经脉循行部位的其他病证。如：咳血，气喘，舌干，咽喉肿痛，水肿，大便秘结，泄泻，腰痛，脊股内后侧痛，痿弱无力，足心热等病证。","xu":"耳鸣、健忘、尿频、腿酸、性欲减退、便秘、元气不足、易疲劳、骨质疏松，天寒手脚冰冷、脚气等。 "},
			"9":{"id":9,"nam":"手厥阴心包经","shi":"心包发炎、胸闷、心痛、上脘异常、喜欢睡、心血管病变、易头昏、头痛等。","time":"戌时（19点至21点）—心包经旺。戌时护心脏，减压心舒畅； “心包为心之外膜，附有脉络，气血通行之道。邪不能容，容之心伤。”心包是心的保护组织，又是气血通道。心包经戌时最兴旺，可清除心脏周围外邪，使心脏处于完好状态。此时一定要保持心情舒畅：看书听音乐、或做SPA、跳舞、耍太极……放松心情，释放压力。 ","treat":"主治心、胸、胃、神志病以及经脉循行部位的其他病证。如心痛，胸闷，心悸，心烦，癫狂，腋肿，肘臂挛急等证。","xu":"大多表现为润滑液分泌不足、心跳异常、气喘、失眠多梦、心悸亢奋、语言障碍、手掌发热等。 "}
		}
}
